modules/inputconditioner.v
//------------------------------------------------------------------------
// Input Conditioner
//    1) Synchronizes input to clock domain
//    2) Debounces input
//    3) Creates pulses at edge transitions
//------------------------------------------------------------------------

module inputconditioner
(
input 	    clk,            // Clock domain to synchronize input to
input	    noisysignal,    // (Potentially) noisy input signal
output reg conditioned,    // Conditioned output signal
output reg  positiveedge,   // 1 clk pulse at rising edge of conditioned
output reg  negativeedge    // 1 clk pulse at falling edge of conditioned
);


    initial positiveedge = 0;
    initial negativeedge = 0;
    initial conditioned = 0;

    parameter counterwidth = 3; // Counter size, in bits, >= log2(waittime)
    parameter waittime = 3;     // Debounce delay, in clock cycles
    
    reg[counterwidth-1:0] counter = 0;
    reg synchronizer0 = 0;
    reg synchronizer1 = 0;
    
    reg[waittime-1:0] inputFilter;

    always@(posedge clk)
        inputFilter[0] <= noisysignal;

    generate
    genvar i;
    for (i = 1; i<waittime;i=i+1 ) begin
        always@(posedge clk)
            inputFilter[i] <= inputFilter[i-1];
    end
    endgenerate

    wire h1;
    wire h2;
    //MUST CHANGE IF COUNTERWIDTH CHANGES
    and outputsignal(h1,inputFilter[0],inputFilter[1],inputFilter[2]);
    nor outputsignal1(h2,inputFilter[0],inputFilter[1],inputFilter[2]);

    reg holder;

    wire timer_clock;
    or orgate(timer_clock,h1,h2);

    always@(posedge timer_clock)
        conditioned <= noisysignal;


    reg signal;
    // //Posedge for conditioned button
    // always @(posedge clk) begin
    //     if(conditioned == synchronizer1)
    //         counter <= 0;

    //     else begin
    //         if( counter == waittime) begin
    //             counter <= 0;
    //             conditioned <= synchronizer1;
    //         end

    //         else 
    //             counter <= counter+1;
    //     end
    //     synchronizer0 <= noisysignal;
    //     synchronizer1 <= synchronizer0;
    // end    
    //     //https://www.edaboard.com/showthread.php?40349-how-can-i-detect-the-positive-edge-of-a-signal-in-verilog
    always @(posedge clk or negedge conditioned or posedge conditioned)
        begin
        if (~conditioned)
            signal <= 1'b0;
        else
            signal <= 1'b1;
        negativeedge <= ~conditioned & (signal);
        positiveedge <= conditioned & (~signal);

        end

endmodule

modules/inputconditioner.t.v
`timescale 1 ns / 1 ps

//------------------------------------------------------------------------
// Input Conditioner test bench
//------------------------------------------------------------------------
`include "inputconditioner.v"

module testConditioner();

    reg clk;
    reg pin;
    wire conditioned;
    wire rising;
    wire falling;

    inputconditioner dut(.clk(clk),
    			         .noisysignal(pin),
			             .conditioned(conditioned),
			             .positiveedge(rising),
			             .negativeedge(falling));
    // Generate clock (50MHz)
    initial clk = 1;
    always #10 clk=!clk;    // 50MHz Clock

    initial begin
    $dumpfile("inputconditioner.vcd");
        $dumpvars(0, dut);
    repeat(10) begin
    pin = 0;
	$display("%t | %d | %d | %d | %d | %d |", $time, clk, pin, conditioned, rising, falling); #20;
	end
    repeat(20) begin
        pin = 1;
	    $display("%t | %d | %d | %d | %d | %d |", $time, clk, pin, conditioned, rising, falling); #20;
	end
    repeat(10) begin
    pin = 0;
	$display("%t | %d | %d | %d | %d | %d |", $time, clk, pin, conditioned, rising, falling); #20;
    end
    repeat(5) begin
        pin = 1;
	    $display("%t | %d | %d | %d | %d | %d |", $time, clk, pin, conditioned, rising, falling); #20;
	end

    repeat(10) begin
    pin = 0;
	$display("%t | %d | %d | %d | %d | %d |", $time, clk, pin, conditioned, rising, falling); #20;
	end

    repeat(10) begin   //Ensure super noisy singal does not send posedge or negedge signals
        pin = 1;
	    $display("%t | %d | %d | %d | %d | %d |", $time, clk, pin, conditioned, rising, falling); #20;
        pin = 0;
	    $display("%t | %d | %d | %d | %d | %d |", $time, clk, pin, conditioned, rising, falling); #20;
	end

    repeat(10) begin
    pin = 0;
	$display("%t | %d | %d | %d | %d | %d |", $time, clk, pin, conditioned, rising, falling); #20;
	end

    repeat(5) begin  //Short Signal _too short for wait-time so should not send posedge or negedge outputs
        pin = 1;
	    $display("%t | %d | %d | %d | %d | %d |", $time, clk, pin, conditioned, rising, falling); #20;
	end

    repeat(10) begin
    pin = 0;
	$display("%t | %d | %d | %d | %d | %d |", $time, clk, pin, conditioned, rising, falling); #20;
	end

    repeat(4) begin  //Short Signal _too short for wait-time so should not send posedge or negedge outputs
        pin = 1;
	    $display("%t | %d | %d | %d | %d | %d |", $time, clk, pin, conditioned, rising, falling); #20;
	end

    repeat(10) begin
    pin = 0;
	$display("%t | %d | %d | %d | %d | %d |", $time, clk, pin, conditioned, rising, falling); #20;
	end

    repeat(3) begin  //Short Signal _too short for wait-time so should not send posedge or negedge outputs
        pin = 1;
	    $display("%t | %d | %d | %d | %d | %d |", $time, clk, pin, conditioned, rising, falling); #20;
	end

    repeat(10) begin
    pin = 0;
	$display("%t | %d | %d | %d | %d | %d |", $time, clk, pin, conditioned, rising, falling); #20;
	end

	$display("... more execution (see waveform)");
		$finish();
	end

endmodule

modules/inputconditioner.vcd
$date
	Tue Nov 19 17:12:43 2019
$end
$version
	Icarus Verilog
$end
$timescale
	1ps
$end
$scope module testConditioner $end
$scope module dut $end
$var wire 1 ! clk $end
$var wire 1 " h1 $end
$var wire 1 # h2 $end
$var wire 1 $ noisysignal $end
$var wire 1 % timer_clock $end
$var reg 1 & conditioned $end
$var reg 3 ' counter [2:0] $end
$var reg 3 ( inputFilter [2:0] $end
$var reg 1 ) negativeedge $end
$var reg 1 * positiveedge $end
$var reg 1 + signal $end
$var reg 1 , synchronizer0 $end
$var reg 1 - synchronizer1 $end
$scope begin genblk1[1] $end
$upscope $end
$scope begin genblk1[2] $end
$upscope $end
$upscope $end
$upscope $end
$enddefinitions $end
#0
$dumpvars
0-
0,
0+
0*
x)
bx0 (
b0 '
0&
x%
0$
x#
0"
1!
$end
#10000
0!
#20000
bx00 (
0)
1!
#30000
0!
#40000
1%
1#
b0 (
1!
#50000
0!
#60000
1!
#70000
0!
#80000
1!
#90000
0!
#100000
1!
#110000
0!
#120000
1!
#130000
0!
#140000
1!
#150000
0!
#160000
1!
#170000
0!
#180000
1!
#190000
0!
#200000
0%
0#
b1 (
1!
1$
#210000
0!
#220000
b11 (
1!
#230000
0!
#240000
1+
1*
1&
1%
1"
b111 (
1!
#250000
0!
#260000
0*
1!
#270000
0!
#280000
1!
#290000
0!
#300000
1!
#310000
0!
#320000
1!
#330000
0!
#340000
1!
#350000
0!
#360000
1!
#370000
0!
#380000
1!
#390000
0!
#400000
1!
#410000
0!
#420000
1!
#430000
0!
#440000
1!
#450000
0!
#460000
1!
#470000
0!
#480000
1!
#490000
0!
#500000
1!
#510000
0!
#520000
1!
#530000
0!
#540000
1!
#550000
0!
#560000
1!
#570000
0!
#580000
1!
#590000
0!
#600000
0%
0"
b110 (
1!
0$
#610000
0!
#620000
b100 (
1!
#630000
0!
#640000
0+
1)
0&
1%
1#
b0 (
1!
#650000
0!
#660000
0)
1!
#670000
0!
#680000
1!
#690000
0!
#700000
1!
#710000
0!
#720000
1!
#730000
0!
#740000
1!
#750000
0!
#760000
1!
#770000
0!
#780000
1!
#790000
0!
#800000
0%
0#
b1 (
1!
1$
#810000
0!
#820000
b11 (
1!
#830000
0!
#840000
1+
1*
1&
1%
1"
b111 (
1!
#850000
0!
#860000
0*
1!
#870000
0!
#880000
1!
#890000
0!
#900000
0%
0"
b110 (
1!
0$
#910000
0!
#920000
b100 (
1!
#930000
0!
#940000
0+
1)
0&
1%
1#
b0 (
1!
#950000
0!
#960000
0)
1!
#970000
0!
#980000
1!
#990000
0!
#1000000
1!
#1010000
0!
#1020000
1!
#1030000
0!
#1040000
1!
#1050000
0!
#1060000
1!
#1070000
0!
#1080000
1!
#1090000
0!
#1100000
0%
0#
b1 (
1!
1$
#1110000
0!
#1120000
b10 (
1!
0$
#1130000
0!
#1140000
b101 (
1!
1$
#1150000
0!
#1160000
b10 (
1!
0$
#1170000
0!
#1180000
b101 (
1!
1$
#1190000
0!
#1200000
b10 (
1!
0$
#1210000
0!
#1220000
b101 (
1!
1$
#1230000
0!
#1240000
b10 (
1!
0$
#1250000
0!
#1260000
b101 (
1!
1$
#1270000
0!
#1280000
b10 (
1!
0$
#1290000
0!
#1300000
b101 (
1!
1$
#1310000
0!
#1320000
b10 (
1!
0$
#1330000
0!
#1340000
b101 (
1!
1$
#1350000
0!
#1360000
b10 (
1!
0$
#1370000
0!
#1380000
b101 (
1!
1$
#1390000
0!
#1400000
b10 (
1!
0$
#1410000
0!
#1420000
b101 (
1!
1$
#1430000
0!
#1440000
b10 (
1!
0$
#1450000
0!
#1460000
b101 (
1!
1$
#1470000
0!
#1480000
b10 (
1!
0$
#1490000
0!
#1500000
b100 (
1!
#1510000
0!
#1520000
1%
1#
b0 (
1!
#1530000
0!
#1540000
1!
#1550000
0!
#1560000
1!
#1570000
0!
#1580000
1!
#1590000
0!
#1600000
1!
#1610000
0!
#1620000
1!
#1630000
0!
#1640000
1!
#1650000
0!
#1660000
1!
#1670000
0!
#1680000
1!
#1690000
0!
#1700000
0%
0#
b1 (
1!
1$
#1710000
0!
#1720000
b11 (
1!
#1730000
0!
#1740000
1+
1*
1&
1%
1"
b111 (
1!
#1750000
0!
#1760000
0*
1!
#1770000
0!
#1780000
1!
#1790000
0!
#1800000
0%
0"
b110 (
1!
0$
#1810000
0!
#1820000
b100 (
1!
#1830000
0!
#1840000
0+
1)
0&
1%
1#
b0 (
1!
#1850000
0!
#1860000
0)
1!
#1870000
0!
#1880000
1!
#1890000
0!
#1900000
1!
#1910000
0!
#1920000
1!
#1930000
0!
#1940000
1!
#1950000
0!
#1960000
1!
#1970000
0!
#1980000
1!
#1990000
0!
#2000000
0%
0#
b1 (
1!
1$
#2010000
0!
#2020000
b11 (
1!
#2030000
0!
#2040000
1+
1*
1&
1%
1"
b111 (
1!
#2050000
0!
#2060000
0*
1!
#2070000
0!
#2080000
0%
0"
b110 (
1!
0$
#2090000
0!
#2100000
b100 (
1!
#2110000
0!
#2120000
0+
1)
0&
1%
1#
b0 (
1!
#2130000
0!
#2140000
0)
1!
#2150000
0!
#2160000
1!
#2170000
0!
#2180000
1!
#2190000
0!
#2200000
1!
#2210000
0!
#2220000
1!
#2230000
0!
#2240000
1!
#2250000
0!
#2260000
1!
#2270000
0!
#2280000
0%
0#
b1 (
1!
1$
#2290000
0!
#2300000
b11 (
1!
#2310000
0!
#2320000
1+
1*
1&
1%
1"
b111 (
1!
#2330000
0!
#2340000
0%
0"
b110 (
0*
1!
0$
#2350000
0!
#2360000
b100 (
1!
#2370000
0!
#2380000
0+
1)
0&
1%
1#
b0 (
1!
#2390000
0!
#2400000
0)
1!
