modules/inputconditioner.v
//------------------------------------------------------------------------
// Input Conditioner
//    1) Synchronizes input to clock domain
//    2) Debounces input
//    3) Creates pulses at edge transitions
//------------------------------------------------------------------------

module inputconditioner
(
input 	    clk,            // Clock domain to synchronize input to
input	    noisysignal,    // (Potentially) noisy input signal
output reg  conditioned,    // Conditioned output signal
output reg  positiveedge,   // 1 clk pulse at rising edge of conditioned
output reg  negativeedge    // 1 clk pulse at falling edge of conditioned
);


    initial positiveedge = 0;
    initial negativeedge = 0;
    parameter counterwidth = 3; // Counter size, in bits, >= log2(waittime)
    parameter waittime = 3;     // Debounce delay, in clock cycles
    
    reg[counterwidth-1:0] counter = 0;
    reg synchronizer0 = 0;
    reg synchronizer1 = 0;
    
    reg signal;
    //Posedge for conditioned button
    always @(posedge clk) begin
        if(conditioned == synchronizer1)
            counter <= 0;

        else begin
            if( counter == waittime) begin
                counter <= 0;
                conditioned <= synchronizer1;
            end

            else 
                counter <= counter+1;
        end
        synchronizer0 <= noisysignal;
        synchronizer1 <= synchronizer0;
    end    
        //https://www.edaboard.com/showthread.php?40349-how-can-i-detect-the-positive-edge-of-a-signal-in-verilog
    always @(posedge clk or negedge conditioned)
        begin
        if (~conditioned)
            signal <= 1'b0;
        else
            signal <= 1'b1;
        assign positiveedge = conditioned & (~signal);
        assign negativeedge = ~conditioned & (signal);

        end

endmodule

modules/inputconditioner.t.v
`timescale 1 ns / 1 ps

//------------------------------------------------------------------------
// Input Conditioner test bench
//------------------------------------------------------------------------
`include "inputconditioner.v"

module testConditioner();

    reg clk;
    reg pin;
    wire conditioned;
    wire rising;
    wire falling;

    inputconditioner dut(.clk(clk),
    			         .noisysignal(pin),
			             .conditioned(conditioned),
			             .positiveedge(rising),
			             .negativeedge(falling));
    // Generate clock (50MHz)
    initial clk = 1;
    always #10 clk=!clk;    // 50MHz Clock

    initial begin
    $dumpfile("inputconditioner.vcd");
        $dumpvars(0, dut);
    repeat(10) begin
    pin = 0;
	$display("%t | %d | %d | %d | %d | %d |", $time, clk, pin, conditioned, rising, falling); #20;
	end
    repeat(20) begin
        pin = 1;
	    $display("%t | %d | %d | %d | %d | %d |", $time, clk, pin, conditioned, rising, falling); #20;
	end
    repeat(10) begin
    pin = 0;
	$display("%t | %d | %d | %d | %d | %d |", $time, clk, pin, conditioned, rising, falling); #20;
    end
    repeat(5) begin
        pin = 1;
	    $display("%t | %d | %d | %d | %d | %d |", $time, clk, pin, conditioned, rising, falling); #20;
	end

    repeat(10) begin
    pin = 0;
	$display("%t | %d | %d | %d | %d | %d |", $time, clk, pin, conditioned, rising, falling); #20;
	end

    repeat(10) begin   //Ensure super noisy singal does not send posedge or negedge signals
        pin = 1;
	    $display("%t | %d | %d | %d | %d | %d |", $time, clk, pin, conditioned, rising, falling); #20;
        pin = 0;
	    $display("%t | %d | %d | %d | %d | %d |", $time, clk, pin, conditioned, rising, falling); #20;
	end

    repeat(10) begin
    pin = 0;
	$display("%t | %d | %d | %d | %d | %d |", $time, clk, pin, conditioned, rising, falling); #20;
	end

    repeat(5) begin  //Short Signal _too short for wait-time so should not send posedge or negedge outputs
        pin = 1;
	    $display("%t | %d | %d | %d | %d | %d |", $time, clk, pin, conditioned, rising, falling); #20;
	end

    repeat(10) begin
    pin = 0;
	$display("%t | %d | %d | %d | %d | %d |", $time, clk, pin, conditioned, rising, falling); #20;
	end

    repeat(4) begin  //Short Signal _too short for wait-time so should not send posedge or negedge outputs
        pin = 1;
	    $display("%t | %d | %d | %d | %d | %d |", $time, clk, pin, conditioned, rising, falling); #20;
	end

    repeat(10) begin
    pin = 0;
	$display("%t | %d | %d | %d | %d | %d |", $time, clk, pin, conditioned, rising, falling); #20;
	end

    repeat(3) begin  //Short Signal _too short for wait-time so should not send posedge or negedge outputs
        pin = 1;
	    $display("%t | %d | %d | %d | %d | %d |", $time, clk, pin, conditioned, rising, falling); #20;
	end

    repeat(10) begin
    pin = 0;
	$display("%t | %d | %d | %d | %d | %d |", $time, clk, pin, conditioned, rising, falling); #20;
	end

	$display("... more execution (see waveform)");
		$finish();
	end

endmodule

modules/inputconditioner.vcd
$date
	Mon Nov 18 20:31:50 2019
$end
$version
	Icarus Verilog
$end
$timescale
	1s
$end
$scope module testConditioner $end
$scope module dut $end
$var wire 1 ! clk $end
$var wire 1 " noisysignal $end
$var reg 1 # conditioned $end
$var reg 3 $ counter [2:0] $end
$var reg 1 % negativeedge $end
$var reg 1 & positiveedge $end
$var reg 1 ' signal $end
$var reg 1 ( synchronizer0 $end
$var reg 1 ) synchronizer1 $end
$upscope $end
$upscope $end
$enddefinitions $end
#0
$dumpvars
0)
0(
0'
0&
x%
b0 $
0#
0"
1!
$end
#10
0!
#20
0%
1!
#30
0!
#40
1!
#50
0!
#60
1!
#70
0!
#80
1!
#90
0!
#100
1!
#110
0!
#120
1!
#130
0!
#140
1!
#150
0!
#160
1!
#170
0!
#180
1!
#190
0!
#200
1(
1!
1"
#210
0!
#220
1)
1!
#230
0!
#240
b1 $
1!
#250
0!
#260
b10 $
1!
#270
0!
#280
b11 $
1!
#290
0!
#300
1'
1&
1#
b0 $
1!
#310
0!
#320
0&
1!
#330
0!
#340
1!
#350
0!
#360
1!
#370
0!
#380
1!
#390
0!
#400
1!
#410
0!
#420
1!
#430
0!
#440
1!
#450
0!
#460
1!
#470
0!
#480
1!
#490
0!
#500
1!
#510
0!
#520
1!
#530
0!
#540
1!
#550
0!
#560
1!
#570
0!
#580
1!
#590
0!
#600
0(
1!
0"
#610
0!
#620
0)
1!
#630
0!
#640
b1 $
1!
#650
0!
#660
b10 $
1!
#670
0!
#680
b11 $
1!
#690
0!
#700
0'
1%
0#
b0 $
1!
#710
0!
#720
0%
1!
#730
0!
#740
1!
#750
0!
#760
1!
#770
0!
#780
1!
#790
0!
#800
1(
1!
1"
#810
0!
#820
1)
1!
#830
0!
#840
b1 $
1!
#850
0!
#860
b10 $
1!
#870
0!
#880
b11 $
1!
#890
0!
#900
1'
1&
0(
1#
b0 $
1!
0"
#910
0!
#920
0)
0&
1!
#930
0!
#940
b1 $
1!
#950
0!
#960
b10 $
1!
#970
0!
#980
b11 $
1!
#990
0!
#1000
0'
1%
0#
b0 $
1!
#1010
0!
#1020
0%
1!
#1030
0!
#1040
1!
#1050
0!
#1060
1!
#1070
0!
#1080
1!
#1090
0!
#1100
1(
1!
1"
#1110
0!
#1120
1)
0(
1!
0"
#1130
0!
#1140
0)
1(
b1 $
1!
1"
#1150
0!
#1160
1)
0(
b0 $
1!
0"
#1170
0!
#1180
0)
1(
b1 $
1!
1"
#1190
0!
#1200
1)
0(
b0 $
1!
0"
#1210
0!
#1220
0)
1(
b1 $
1!
1"
#1230
0!
#1240
1)
0(
b0 $
1!
0"
#1250
0!
#1260
0)
1(
b1 $
1!
1"
#1270
0!
#1280
1)
0(
b0 $
1!
0"
#1290
0!
#1300
0)
1(
b1 $
1!
1"
#1310
0!
#1320
1)
0(
b0 $
1!
0"
#1330
0!
#1340
0)
1(
b1 $
1!
1"
#1350
0!
#1360
1)
0(
b0 $
1!
0"
#1370
0!
#1380
0)
1(
b1 $
1!
1"
#1390
0!
#1400
1)
0(
b0 $
1!
0"
#1410
0!
#1420
0)
1(
b1 $
1!
1"
#1430
0!
#1440
1)
0(
b0 $
1!
0"
#1450
0!
#1460
0)
1(
b1 $
1!
1"
#1470
0!
#1480
1)
0(
b0 $
1!
0"
#1490
0!
#1500
0)
b1 $
1!
#1510
0!
#1520
b0 $
1!
#1530
0!
#1540
1!
#1550
0!
#1560
1!
#1570
0!
#1580
1!
#1590
0!
#1600
1!
#1610
0!
#1620
1!
#1630
0!
#1640
1!
#1650
0!
#1660
1!
#1670
0!
#1680
1!
#1690
0!
#1700
1(
1!
1"
#1710
0!
#1720
1)
1!
#1730
0!
#1740
b1 $
1!
#1750
0!
#1760
b10 $
1!
#1770
0!
#1780
b11 $
1!
#1790
0!
#1800
1'
1&
0(
1#
b0 $
1!
0"
#1810
0!
#1820
0)
0&
1!
#1830
0!
#1840
b1 $
1!
#1850
0!
#1860
b10 $
1!
#1870
0!
#1880
b11 $
1!
#1890
0!
#1900
0'
1%
0#
b0 $
1!
#1910
0!
#1920
0%
1!
#1930
0!
#1940
1!
#1950
0!
#1960
1!
#1970
0!
#1980
1!
#1990
0!
#2000
1(
1!
1"
#2010
0!
#2020
1)
1!
#2030
0!
#2040
b1 $
1!
#2050
0!
#2060
b10 $
1!
#2070
0!
#2080
0(
b11 $
1!
0"
#2090
0!
#2100
1'
1&
0)
1#
b0 $
1!
#2110
0!
#2120
b1 $
0&
1!
#2130
0!
#2140
b10 $
1!
#2150
0!
#2160
b11 $
1!
#2170
0!
#2180
0'
1%
0#
b0 $
1!
#2190
0!
#2200
0%
1!
#2210
0!
#2220
1!
#2230
0!
#2240
1!
#2250
0!
#2260
1!
#2270
0!
#2280
1(
1!
1"
#2290
0!
#2300
1)
1!
#2310
0!
#2320
b1 $
1!
#2330
0!
#2340
0(
b10 $
1!
0"
#2350
0!
#2360
0)
b11 $
1!
#2370
0!
#2380
b0 $
1!
