modules/inputconditioner.v
//------------------------------------------------------------------------
// Input Conditioner
//    1) Synchronizes input to clock domain
//    2) Debounces input
//    3) Creates pulses at edge transitions
//------------------------------------------------------------------------

module inputconditioner
(
input 	    clk,            // Clock domain to synchronize input to
input	    noisysignal,    // (Potentially) noisy input signal
output reg  conditioned,    // Conditioned output signal
output reg  positiveedge,   // 1 clk pulse at rising edge of conditioned
output reg  negativeedge    // 1 clk pulse at falling edge of conditioned
);


    parameter counterwidth = 3; // Counter size, in bits, >= log2(waittime)
    parameter waittime = 3;     // Debounce delay, in clock cycles
    
    reg[counterwidth-1:0] counter = 0;
    reg synchronizer0 = 0;
    reg synchronizer1 = 0;
    
    wire reg negcon;
    reg sig_delay;

    //Posedge for conditioned button
    always @(posedge clk) begin
        if(conditioned == synchronizer1)
            counter <= 0;

        else begin
            if( counter == waittime) begin
                counter <= 0;
                conditioned <= synchronizer1;
            end

            else 
                counter <= counter+1;
        end
        synchronizer0 <= noisysignal;
        synchronizer1 <= synchronizer0;
        sig_delay <= conditioned;
        positiveedge <= ~sig_delay & conditioned;
        negativeedge <= sig_delay & ~conditioned;
    end      
endmodule

modules/inputconditioner.t.v
//------------------------------------------------------------------------
// Input Conditioner test bench
//------------------------------------------------------------------------
`include "inputconditioner.v" 

module testConditioner();

    reg clk;
    reg pin;
    wire conditioned;
    wire rising;
    wire falling;
    
    inputconditioner dut(.clk(clk),
    			         .noisysignal(pin),
			             .conditioned(conditioned),
			             .positiveedge(rising),
			             .negativeedge(falling));
    // Generate clock (50MHz)
    initial clk = 0;
    always #10 clk=!clk;    // 50MHz Clock
    
    initial begin
    $dumpfile("inputconditioner.vcd");
        $dumpvars(0, dut);
    repeat(10) begin 
    pin = 0;
	$display("%t | %d | %d | %d | %d |%d |", $time, clk, pin, conditioned, rising, falling); #10;
	end
    repeat(20) begin 
        pin = 1;
	    $display("%t | %d | %d | %d | %d |%d |", $time, clk, pin, conditioned, rising, falling); #10;
	end
    repeat(50) begin 
    pin = 0;
	$display("%t | %d | %d | %d | %d |%d |", $time, clk, pin, conditioned, rising, falling); #10;
	end
	$display("... more execution (see waveform)");
		$finish();
	end
    
endmodule

modules/inputconditioner.vcd
$date
	Sat Nov 16 21:28:12 2019
$end
$version
	Icarus Verilog
$end
$timescale
	1s
$end
$scope module testConditioner $end
$scope module dut $end
$var wire 1 ! clk $end
$var wire 1 " noisysignal $end
$var reg 1 # conditioned $end
$var reg 3 $ counter [2:0] $end
$var reg 1 % negativeedge $end
$var reg 1 & positiveedge $end
$var reg 1 ' sig_delay $end
$var reg 1 ( synchronizer0 $end
$var reg 1 ) synchronizer1 $end
$upscope $end
$upscope $end
$enddefinitions $end
#0
$dumpvars
0)
0(
x'
x&
x%
b0 $
x#
0"
0!
$end
#10
b1 $
1!
#20
0!
#30
b10 $
1!
#40
0!
#50
b11 $
1!
#60
0!
#70
0#
b0 $
1!
#80
0!
#90
0&
0'
1!
#100
1"
0!
#110
0%
1(
1!
#120
0!
#130
1)
1!
#140
0!
#150
b1 $
1!
#160
0!
#170
b10 $
1!
#180
0!
#190
b11 $
1!
#200
0!
#210
1#
b0 $
1!
#220
0!
#230
1&
1'
1!
#240
0!
#250
0&
1!
#260
0!
#270
1!
#280
0!
#290
1!
#300
0"
0!
#310
0(
1!
#320
0!
#330
0)
1!
#340
0!
#350
b1 $
1!
#360
0!
#370
b10 $
1!
#380
0!
#390
b11 $
1!
#400
0!
#410
0#
b0 $
1!
#420
0!
#430
1%
0'
1!
#440
0!
#450
0%
1!
