modules/enable_not.v
module enablenot(
input data_in,
input enable,
output reg out
);
always @ (enable) 
    if (enable)
        out <= ~data_in;
    else
        out <= data_in;
    
endmodule

modules/dflipflop.v
module d_flipflop(
input D,
input clk,
input enable,
output reg Q
);
    initial Q =  0;
    always @ (negedge clk) begin
        if (enable)begin
            Q <= D;
            end
         else begin
            Q <= Q;
        end
    end
endmodule

modules/addresslatch.v
module Address_Latch(
input [7:0] D,
input clk,
input enable,
output reg[6:0] Q
);
    initial Q =  0;
    always @ (posedge clk) begin
        if (enable)begin
            Q <= D[6:0];
            end
         else begin
            Q <= Q;
        end
    end
endmodule

modules/statemachine.v
//------------------------------------------------------------------------
// Finite State Machine for SPI Module
// Contributors: @aditya-sudhakar, @coreyacl, @Kristya
//------------------------------------------------------------------------

module statemachine(
    input clk,
    input cs,
    input shiftregout,
    output reg RW,
    output misobuff,
    output mem_we,
    output reg add_latch_we,
    input serialDataIn
);
parameter t_count = 15;


//SOLVE KNOWN VALUE ISSUE
reg[t_count-1:0] tim;
initial tim = 0;
wire out;
wire enable;
wire CS_N;

not notCS(CS_N,cs);


// Timer for 15
nor yep(out,tim[0],tim[1],tim[2],tim[3],tim[4],tim[5],tim[6],tim[7],tim[8],tim[9],tim[10],tim[11],tim[12],tim[13],tim[14]);
and orgate(enable,out,CS_N);

always@(posedge clk)
    tim[0] <= enable;

generate
genvar i;
for (i = 1;i<t_count ;i = i +1 ) begin
wire res;
and andgateTimer(res,CS_N,tim[i-1]);
    always@(posedge clk)
        tim[i] <= res;
end
endgenerate

// Signals the RW phase of the message
always@(tim[7])
    add_latch_we <= tim[7];

wire rw_enable;

wire ifRead;

and andgate1(ifRead,tim[8],serialDataIn);

// Load parallel data in
always@(negedge clk)
    RW <= ifRead;

// Signals end of message
// and rwandgate(mem_we,RW,tim[t_count-1]);


endmodule

modules/datamemory.v
//------------------------------------------------------------------------
// Data Memory
//   Positive edge triggered
//   dataOut always has the value mem[address]
//   If writeEnable is true, writes dataIn to mem[address]
//------------------------------------------------------------------------

module datamemory
#(
    parameter addresswidth  = 7,
    parameter depth         = 2**addresswidth,
    parameter width         = 8
)
(
    input 		                clk,
    output reg [width-1:0]      dataOut,
    input [addresswidth-1:0]    address,
    input                       writeEnable,
    input [width-1:0]           dataIn,
    input                       reset
);

    reg [width-1:0] memory [depth-1:0];

    always @(posedge clk) begin
        if(writeEnable)
            memory[address] <= dataIn;
            dataOut <= memory[address];
    end


    //SO I've read that FPGAs have no known value for any registers
    //on startup so it's common practice to set a reset line to necessary
    //modules in order to set them to a known value -> Stack Overflow
    reg[31:0] k;
    always@(posedge reset)begin
      if (reset) begin
        for (k =0 ;k<3'b111 ;k = k + 1 ) begin
          memory[k] = 8'b0;
          end
          // memory[7] = 8'b101010; //points to the begening of the stack
          //                      //source -> Mars
      end
    end


endmodule

modules/shiftregmodes.v
`ifndef SHIFTREGMODES_V
`define SHIFTREGMODES_V

//List of input cases
`define HOLD      2'b00    //hold current state
`define PLOAD     2'b01    //Parallel Load: parallelIn replaces entire shift register contents
`define LSHIFT    2'b10    //Left Shift: serialIn becomes new LSB, MSB is dropped
`define RSHIFT    2'b11    //Right Shift: serialIn become the new MSB, LSB is dropped

`endif

modules/shiftregister.v
//------------------------------------------------------------------------
// Shift Register
//   Parameterized width (in bits)
//   Shift register can operate in two modes:
//      - serial in, parallel out
//      - parallel in, serial out
//------------------------------------------------------------------------

`include "shiftregmodes.v"

module shiftregister
#(parameter width = 8)
(
input               clk,                // FPGA Clock
input               peripheralClkEdge,  // Edge indicator
input               parallelLoad,       // 1 = Load shift reg with parallelDataIn
input  [width-1:0]  parallelDataIn,     // Load shift reg in parallel
input               serialDataIn,       // Load shift reg serially
output   reg [width-1:0]  parallelDataOut,    // Shift reg data contents
output   reg        serialDataOut,      // Positive edge synchronized
output   reg        rewr                  //1 for write, 0 for read

);
    reg[width-1:0] mem;

    always @(posedge parallelLoad)
        mem <= parallelDataIn;

    always @(parallelDataIn[7])
        rewr <= parallelDataIn[7];

    always @(peripheralClkEdge) begin

        parallelDataOut <= {parallelDataOut[6:0], serialDataIn};
    end

    always @(peripheralClkEdge) begin

      serialDataOut <= mem[7];
      mem <= {mem[6:0], 1'b0};
    end

endmodule

modules/inputconditioner.v
//------------------------------------------------------------------------
// Input Conditioner
//    1) Synchronizes input to clock domain
//    2) Debounces input
//    3) Creates pulses at edge transitions
//------------------------------------------------------------------------

module inputconditioner
(
input 	    clk,            // Clock domain to synchronize input to
input	    noisysignal,    // (Potentially) noisy input signal
output reg conditioned,    // Conditioned output signal
output reg  positiveedge,   // 1 clk pulse at rising edge of conditioned
output reg  negativeedge    // 1 clk pulse at falling edge of conditioned
);


    initial positiveedge = 0;
    initial negativeedge = 0;
    initial conditioned = 0;

    parameter counterwidth = 3; // Counter size, in bits, >= log2(waittime)
    parameter waittime = 3;     // Debounce delay, in clock cycles
    
    reg[counterwidth-1:0] counter = 0;
    reg synchronizer0 = 0;
    reg synchronizer1 = 0;
    
    reg[waittime-1:0] inputFilter;

    always@(posedge clk)
        inputFilter[0] <= noisysignal;

    generate
    genvar i;
    for (i = 1; i<waittime;i=i+1 ) begin
        always@(posedge clk)
            inputFilter[i] <= inputFilter[i-1];
    end
    endgenerate

    wire h1;
    wire h2;
    //MUST CHANGE IF COUNTERWIDTH CHANGES
    and outputsignal(h1,inputFilter[0],inputFilter[1],inputFilter[2]);
    nor outputsignal1(h2,inputFilter[0],inputFilter[1],inputFilter[2]);

    reg holder;

    wire timer_clock;
    or orgate(timer_clock,h1,h2);

    always@(posedge timer_clock)
        conditioned <= noisysignal;


    reg signal;
    // //Posedge for conditioned button
    // always @(posedge clk) begin
    //     if(conditioned == synchronizer1)
    //         counter <= 0;

    //     else begin
    //         if( counter == waittime) begin
    //             counter <= 0;
    //             conditioned <= synchronizer1;
    //         end

    //         else 
    //             counter <= counter+1;
    //     end
    //     synchronizer0 <= noisysignal;
    //     synchronizer1 <= synchronizer0;
    // end    
    //     //https://www.edaboard.com/showthread.php?40349-how-can-i-detect-the-positive-edge-of-a-signal-in-verilog
    always @(posedge clk or negedge conditioned or posedge conditioned)
        begin
        if (~conditioned)
            signal <= 1'b0;
        else
            signal <= 1'b1;
        negativeedge <= ~conditioned & (signal);
        positiveedge <= conditioned & (~signal);

        end

endmodule

modules/spimemory.v
//------------------------------------------------------------------------
// SPI Memory
//------------------------------------------------------------------------
`include "inputconditioner.v"
`include "statemachine.v"
`include "shiftregister.v"
`include "datamemory.v"
`include "addresslatch.v"
`include "dflipflop.v"
`include "enable_not.v"

module spiMemory
(
    input           clk,        // FPGA clock
    input           sclk_pin,   // SPI clock
    input           cs_pin,     // SPI chip select
    output          miso_pin,   // SPI master in slave out
    input           mosi_pin,   // SPI master out slave in
    input           reset,      // Reset pin
    output [3:0]    leds        // LEDs for debugging
);
    wire[7:0] dataMemOut;
    wire Q_S_out;
    wire cond_cs;
    wire cond_sclk;
    wire cond_mosi;
    wire posedge0;
    wire posedge1;
    wire posedge2;
    wire negedge0;
    wire negedge1;
    wire negedge2;
    wire[6:0] data_address;
    wire[7:0] parallelDataOut;
    wire serialDataOut;

    wire RW;
    wire misobuff;
    wire mem_we;
    wire add_latch_we;

    inputconditioner MOSI_cond(.conditioned(cond_mosi), .positiveedge(posedge0), .negativeedge(negedge0), .noisysignal(mosi_pin), .clk(clk));
    inputconditioner SCLK_cond(.conditioned(cond_sclk), .positiveedge(posedge1), .negativeedge(negedge1), .noisysignal(sclk_pin), .clk(clk));
    inputconditioner CS_cond(.conditioned(cond_cs), .positiveedge(posedge2), .negativeedge(negedge2), .noisysignal(cs_pin), .clk(clk));

    shiftregister shift_register(.peripheralClkEdge(posedge1), .parallelLoad(RW), .parallelDataIn(dataMemOut), .serialDataIn(cond_mosi), .parallelDataOut(parallelDataOut), .serialDataOut(serialDataOut), .rewr(), .clk(clk));


    datamemory Data_Memory(.dataOut(dataMemOut), .address(data_address), .writeEnable(mem_we), .dataIn(parallelDataOut), .clk(clk), .reset(reset));



    statemachine FSM(.misobuff(misobuff), .mem_we(mem_we), .add_latch_we(add_latch_we), .RW(RW), .shiftregout(parallelDataOut[0]), .cs(cond_cs), .clk(cond_sclk), .serialDataIn(cond_mosi));



    Address_Latch addr_latch(.Q(data_address), .D(parallelDataOut), .enable(add_latch_we), .clk(clk));


    d_flipflop DFF(.Q(Q_S_out), .D(serialDataOut), .enable(negedge1), .clk(cond_sclk));

    and andgate(miso_pin, Q_S_out, 1);

endmodule

modules/spimemory.t.v
`timescale 1 ns / 1 ps

`include "spimemory.v"

module SPI_Test();
    reg           clk;       // FPGA clock
    reg           sclk_pin;   // SPI clock
    reg           cs_pin;     // SPI chip select
    wire          miso_pin;   // SPI master in slave out
    reg           mosi_pin;   // SPI master out slave in
    reg           reset;

    spiMemory dut(.miso_pin(miso_pin),
                  .mosi_pin(mosi_pin),
                  .cs_pin(cs_pin),
                  .sclk_pin(sclk_pin),
                  .clk(clk),
                  .reset(reset));

    // Generate clock (50MHz)
    initial clk = 0;
    always #10 clk=!clk;    // 50MHz Clock
        // Generate clock (50MHz)
    initial sclk_pin = 0;
    always #80 sclk_pin=!sclk_pin;    // 50MHz Clock
        initial begin
        $dumpfile("spimemory.vcd");
        $dumpvars(0, dut);
        $display("testing");
		// $monitor("| %b | %b | %b | %b | %b |", clk, sclk_pin, mosi_pin, cs_pin, miso_pin);
		mosi_pin=1'b0; cs_pin = 8'b1; reset = 1'b0; #80
        mosi_pin=1'b0; cs_pin = 8'b1; #80
        mosi_pin=1'b0; cs_pin = 8'b1; #80
        mosi_pin=1'b0; cs_pin = 8'b1; #80
        mosi_pin=1'b0; cs_pin = 8'b1; reset = 1'b1; #80
	    mosi_pin=1'b0; cs_pin = 8'b1; #80
		mosi_pin=1'b0; cs_pin = 8'b1; reset = 1'b0; #80
		mosi_pin=1'b0; cs_pin = 8'b1; #80
		mosi_pin=1'b1; cs_pin = 8'b0; #80
        mosi_pin=1'b1; cs_pin = 8'b0; #80
	    mosi_pin=1'b0; cs_pin = 8'b0; #80
	    mosi_pin=1'b0; cs_pin = 8'b0; #80
		mosi_pin=1'b1; cs_pin = 8'b0; #80
        mosi_pin=1'b1; cs_pin = 8'b0; #80
	    mosi_pin=1'b0; cs_pin = 8'b0; #80
	    mosi_pin=1'b0; cs_pin = 8'b0; #80
		mosi_pin=1'b1; cs_pin = 8'b0; #80
        mosi_pin=1'b1; cs_pin = 8'b0; #80
	    mosi_pin=1'b0; cs_pin = 8'b0; #80
	    mosi_pin=1'b0; cs_pin = 8'b0; #80
		mosi_pin=1'b1; cs_pin = 8'b0; #80
        mosi_pin=1'b1; cs_pin = 8'b0; #80
	    mosi_pin=1'b0; cs_pin = 8'b0; #80
	    mosi_pin=1'b0; cs_pin = 8'b0; #80
      mosi_pin=1'b1; cs_pin = 8'b0; #80
          mosi_pin=1'b1; cs_pin = 8'b0; #80
        mosi_pin=1'b1; cs_pin = 8'b0; #80
        mosi_pin=1'b1; cs_pin = 8'b0; #80
      mosi_pin=1'b1; cs_pin = 8'b0; #80
          mosi_pin=1'b1; cs_pin = 8'b0; #80
        mosi_pin=1'b0; cs_pin = 8'b0; #80
        mosi_pin=1'b0; cs_pin = 8'b0; #80
      mosi_pin=1'b1; cs_pin = 8'b0; #80
          mosi_pin=1'b1; cs_pin = 8'b0; #80
        mosi_pin=1'b0; cs_pin = 8'b0; #80
        mosi_pin=1'b0; cs_pin = 8'b0; #80
      mosi_pin=1'b1; cs_pin = 8'b0; #80
          mosi_pin=1'b1; cs_pin = 8'b0; #80
        mosi_pin=1'b0; cs_pin = 8'b0; #80
        mosi_pin=1'b0; cs_pin = 8'b0; #80
        mosi_pin=1'b1; cs_pin = 8'b0; #80
            mosi_pin=1'b1; cs_pin = 8'b0; #80
          mosi_pin=1'b0; cs_pin = 8'b0; #80
          mosi_pin=1'b0; cs_pin = 8'b0; #80
        mosi_pin=1'b1; cs_pin = 8'b0; #80
            mosi_pin=1'b1; cs_pin = 8'b0; #80
          mosi_pin=1'b0; cs_pin = 8'b0; #80
          mosi_pin=1'b0; cs_pin = 8'b0; #80
        mosi_pin=1'b1; cs_pin = 8'b0; #80
            mosi_pin=1'b1; cs_pin = 8'b0; #80
          mosi_pin=1'b0; cs_pin = 8'b0; #80
          mosi_pin=1'b0; cs_pin = 8'b0; #80
        mosi_pin=1'b1; cs_pin = 8'b0; #80
            mosi_pin=1'b1; cs_pin = 8'b0; #80
          mosi_pin=1'b0; cs_pin = 8'b0; #80
          mosi_pin=1'b0; cs_pin = 8'b0; #80
		mosi_pin=1'b0; cs_pin = 8'b1; #80
		mosi_pin=1'b0; cs_pin = 8'b1; #10000


		$display("END");
        $finish();
	end
endmodule

modules/spimemory.vcd
$date
	Tue Nov 19 21:33:36 2019
$end
$version
	Icarus Verilog
$end
$timescale
	1ps
$end
$scope module SPI_Test $end
$scope module dut $end
$var wire 1 ! clk $end
$var wire 1 " cs_pin $end
$var wire 4 # leds [3:0] $end
$var wire 1 $ mem_we $end
$var wire 1 % miso_pin $end
$var wire 1 & misobuff $end
$var wire 1 ' mosi_pin $end
$var wire 1 ( reset $end
$var wire 1 ) sclk_pin $end
$var wire 1 * serialDataOut $end
$var wire 1 + posedge2 $end
$var wire 1 , posedge1 $end
$var wire 1 - posedge0 $end
$var wire 8 . parallelDataOut [7:0] $end
$var wire 1 / negedge2 $end
$var wire 1 0 negedge1 $end
$var wire 1 1 negedge0 $end
$var wire 7 2 data_address [6:0] $end
$var wire 8 3 dataMemOut [7:0] $end
$var wire 1 4 cond_sclk $end
$var wire 1 5 cond_mosi $end
$var wire 1 6 cond_cs $end
$var wire 1 7 add_latch_we $end
$var wire 1 8 RW $end
$var wire 1 9 Q_S_out $end
$scope module CS_cond $end
$var wire 1 ! clk $end
$var wire 1 : h1 $end
$var wire 1 ; h2 $end
$var wire 1 " noisysignal $end
$var wire 1 < timer_clock $end
$var reg 1 6 conditioned $end
$var reg 3 = counter [2:0] $end
$var reg 3 > inputFilter [2:0] $end
$var reg 1 / negativeedge $end
$var reg 1 + positiveedge $end
$var reg 1 ? signal $end
$var reg 1 @ synchronizer0 $end
$var reg 1 A synchronizer1 $end
$scope begin genblk1[1] $end
$upscope $end
$scope begin genblk1[2] $end
$upscope $end
$upscope $end
$scope module DFF $end
$var wire 1 0 enable $end
$var wire 1 4 clk $end
$var wire 1 * D $end
$var reg 1 9 Q $end
$upscope $end
$scope module Data_Memory $end
$var wire 1 ! clk $end
$var wire 1 ( reset $end
$var wire 1 $ writeEnable $end
$var wire 8 B dataIn [7:0] $end
$var wire 7 C address [6:0] $end
$var reg 8 D dataOut [7:0] $end
$var reg 32 E k [31:0] $end
$upscope $end
$scope module FSM $end
$var wire 1 F CS_N $end
$var wire 1 6 cs $end
$var wire 1 G enable $end
$var wire 1 H ifRead $end
$var wire 1 $ mem_we $end
$var wire 1 & misobuff $end
$var wire 1 I out $end
$var wire 1 J shiftregout $end
$var wire 1 5 serialDataIn $end
$var wire 1 4 clk $end
$var reg 1 8 RW $end
$var reg 1 7 add_latch_we $end
$var reg 15 K tim [14:0] $end
$scope begin genblk1[1] $end
$var wire 1 L res $end
$upscope $end
$scope begin genblk1[2] $end
$var wire 1 M res $end
$upscope $end
$scope begin genblk1[3] $end
$var wire 1 N res $end
$upscope $end
$scope begin genblk1[4] $end
$var wire 1 O res $end
$upscope $end
$scope begin genblk1[5] $end
$var wire 1 P res $end
$upscope $end
$scope begin genblk1[6] $end
$var wire 1 Q res $end
$upscope $end
$scope begin genblk1[7] $end
$var wire 1 R res $end
$upscope $end
$scope begin genblk1[8] $end
$var wire 1 S res $end
$upscope $end
$scope begin genblk1[9] $end
$var wire 1 T res $end
$upscope $end
$scope begin genblk1[10] $end
$var wire 1 U res $end
$upscope $end
$scope begin genblk1[11] $end
$var wire 1 V res $end
$upscope $end
$scope begin genblk1[12] $end
$var wire 1 W res $end
$upscope $end
$scope begin genblk1[13] $end
$var wire 1 X res $end
$upscope $end
$scope begin genblk1[14] $end
$var wire 1 Y res $end
$upscope $end
$upscope $end
$scope module MOSI_cond $end
$var wire 1 ! clk $end
$var wire 1 Z h1 $end
$var wire 1 [ h2 $end
$var wire 1 ' noisysignal $end
$var wire 1 \ timer_clock $end
$var reg 1 5 conditioned $end
$var reg 3 ] counter [2:0] $end
$var reg 3 ^ inputFilter [2:0] $end
$var reg 1 1 negativeedge $end
$var reg 1 - positiveedge $end
$var reg 1 _ signal $end
$var reg 1 ` synchronizer0 $end
$var reg 1 a synchronizer1 $end
$scope begin genblk1[1] $end
$upscope $end
$scope begin genblk1[2] $end
$upscope $end
$upscope $end
$scope module SCLK_cond $end
$var wire 1 ! clk $end
$var wire 1 b h1 $end
$var wire 1 c h2 $end
$var wire 1 ) noisysignal $end
$var wire 1 d timer_clock $end
$var reg 1 4 conditioned $end
$var reg 3 e counter [2:0] $end
$var reg 3 f inputFilter [2:0] $end
$var reg 1 0 negativeedge $end
$var reg 1 , positiveedge $end
$var reg 1 g signal $end
$var reg 1 h synchronizer0 $end
$var reg 1 i synchronizer1 $end
$scope begin genblk1[1] $end
$upscope $end
$scope begin genblk1[2] $end
$upscope $end
$upscope $end
$scope module addr_latch $end
$var wire 1 ! clk $end
$var wire 1 7 enable $end
$var wire 8 j D [7:0] $end
$var reg 7 k Q [6:0] $end
$upscope $end
$scope module shift_register $end
$var wire 1 ! clk $end
$var wire 8 l parallelDataIn [7:0] $end
$var wire 1 8 parallelLoad $end
$var wire 1 , peripheralClkEdge $end
$var wire 1 5 serialDataIn $end
$var reg 8 m mem [7:0] $end
$var reg 8 n parallelDataOut [7:0] $end
$var reg 1 o rewr $end
$var reg 1 * serialDataOut $end
$upscope $end
$upscope $end
$upscope $end
$enddefinitions $end
#0
$dumpvars
xo
bx0 n
bx0 m
bx l
b0 k
bx0 j
0i
0h
xg
bx f
b0 e
xd
xc
xb
0a
0`
x_
bx ^
b0 ]
x\
x[
xZ
0Y
0X
0W
0V
0U
0T
0S
0R
0Q
0P
0O
0N
0M
0L
b0 K
0J
1I
0H
1G
1F
bx E
bx D
b0 C
bx0 B
0A
0@
x?
bx >
b0 =
x<
x;
x:
09
x8
07
06
05
04
bx 3
b0 2
01
00
0/
bx0 .
0-
0,
0+
x*
0)
0(
0'
z&
0%
z$
bz #
1"
0!
$end
#10000
0Z
0b
0;
0?
bx0 ^
bx0 f
bx1 >
0_
0g
x/
x1
x0
1!
#20000
0!
#30000
bx11 >
bx00 f
bx00 ^
0/
01
00
1!
#40000
0!
#50000
1?
0G
1+
0F
16
1\
1d
1<
1[
1c
1:
b0 ^
b0 f
b111 >
1!
#60000
0!
#70000
0+
1!
#80000
0!
1)
#90000
0d
0c
b1 f
1!
#100000
0!
#110000
b11 f
1!
#120000
0!
#130000
bx00 .
bx00 B
bx00 j
bx00 n
bx00 m
1g
1,
14
1d
1b
b111 f
1!
#140000
0!
#150000
bx000 m
bx000 .
bx000 B
bx000 j
bx000 n
0,
1!
#160000
0!
0)
#170000
0d
0b
b110 f
1!
#180000
0!
#190000
b100 f
1!
#200000
0!
#210000
x%
08
x9
0g
10
04
1d
1c
b0 f
1!
#220000
0!
#230000
00
1!
#240000
0!
1)
#250000
0d
0c
b1 f
1!
#260000
0!
#270000
b11 f
1!
#280000
0!
#290000
bx0000 .
bx0000 B
bx0000 j
bx0000 n
bx0000 m
1g
1,
14
1d
1b
b111 f
1!
#300000
0!
#310000
bx00000 m
bx00000 .
bx00000 B
bx00000 j
bx00000 n
0,
1!
#320000
b1111111 E
0!
1(
0)
#330000
0o
0d
0b
b110 f
b0 3
b0 D
b0 l
1!
#340000
0!
#350000
b100 f
1!
#360000
0!
#370000
0g
10
04
1d
1c
b0 f
1!
#380000
0!
#390000
00
1!
#400000
0!
1)
#410000
0d
0c
b1 f
1!
#420000
0!
#430000
b11 f
1!
#440000
0!
#450000
bx000000 .
bx000000 B
bx000000 j
bx000000 n
bx000000 m
1g
1,
14
1d
1b
b111 f
1!
#460000
0!
#470000
bx0000000 m
bx0000000 .
bx0000000 B
bx0000000 j
bx0000000 n
0,
1!
#480000
0!
0(
0)
#490000
0d
0b
b110 f
1!
#500000
0!
#510000
b100 f
1!
#520000
0!
#530000
0g
10
04
1d
1c
b0 f
1!
#540000
0!
#550000
00
1!
#560000
0!
1)
#570000
0d
0c
b1 f
1!
#580000
0!
#590000
b11 f
1!
#600000
0!
#610000
b0 .
b0 B
b0 j
b0 n
b0 m
1g
1,
14
1d
1b
b111 f
1!
#620000
0!
#630000
0*
0,
1!
#640000
0!
0"
1'
0)
#650000
0\
0d
0<
0[
0b
0:
b1 ^
b110 f
b110 >
1!
#660000
0!
#670000
b100 >
b100 f
b11 ^
1!
#680000
0!
#690000
0%
1_
09
0g
0?
1G
1-
10
1/
1F
15
04
06
1\
1d
1<
1Z
1c
1;
b111 ^
b0 f
b0 >
1!
#700000
0!
#710000
0/
0-
00
1!
#720000
0!
1)
#730000
0d
0c
b1 f
1!
#740000
0!
#750000
b11 f
1!
#760000
0!
#770000
0G
0I
1L
1J
b1 .
b1 B
b1 j
b1 n
b1 K
1g
1,
14
1d
1b
b111 f
1!
#780000
0!
#790000
b11 .
b11 B
b11 j
b11 n
0,
1!
#800000
0!
0'
0)
#810000
0\
0d
0Z
0b
b110 ^
b110 f
1!
#820000
0!
#830000
b100 f
b100 ^
1!
#840000
0!
#850000
0_
0g
11
10
05
04
1\
1d
1[
1c
b0 ^
b0 f
1!
#860000
0!
#870000
01
00
1!
#880000
0!
1)
#890000
0d
0c
b1 f
1!
#900000
0!
#910000
b11 f
1!
#920000
0!
#930000
0L
1M
0J
b110 .
b110 B
b110 j
b110 n
b10 K
1g
1,
14
1d
1b
b111 f
1!
#940000
0!
#950000
b1100 .
b1100 B
b1100 j
b1100 n
0,
1!
#960000
0!
1'
0)
#970000
0\
0d
0[
0b
b1 ^
b110 f
1!
#980000
0!
#990000
b100 f
b11 ^
1!
#1000000
0!
#1010000
1_
0g
1-
10
15
04
1\
1d
1Z
1c
b111 ^
b0 f
1!
#1020000
0!
#1030000
0-
00
1!
#1040000
0!
1)
#1050000
0d
0c
b1 f
1!
#1060000
0!
#1070000
b11 f
1!
#1080000
0!
#1090000
0M
1N
1J
b11001 .
b11001 B
b11001 j
b11001 n
b100 K
1g
1,
14
1d
1b
b111 f
1!
#1100000
0!
#1110000
b110011 .
b110011 B
b110011 j
b110011 n
0,
1!
#1120000
0!
0'
0)
#1130000
0\
0d
0Z
0b
b110 ^
b110 f
1!
#1140000
0!
#1150000
b100 f
b100 ^
1!
#1160000
0!
#1170000
0_
0g
11
10
05
04
1\
1d
1[
1c
b0 ^
b0 f
1!
#1180000
0!
#1190000
01
00
1!
#1200000
0!
1)
#1210000
0d
0c
b1 f
1!
#1220000
0!
#1230000
b11 f
1!
#1240000
0!
#1250000
1O
0N
0J
b1100110 .
b1100110 B
b1100110 j
b1100110 n
b1000 K
1g
1,
14
1d
1b
b111 f
1!
#1260000
0!
#1270000
b11001100 .
b11001100 B
b11001100 j
b11001100 n
0,
1!
#1280000
0!
1'
0)
#1290000
0\
0d
0[
0b
b1 ^
b110 f
1!
#1300000
0!
#1310000
b100 f
b11 ^
1!
#1320000
0!
#1330000
1_
0g
1-
10
15
04
1\
1d
1Z
1c
b111 ^
b0 f
1!
#1340000
0!
#1350000
0-
00
1!
#1360000
0!
1)
#1370000
0d
0c
b1 f
1!
#1380000
0!
#1390000
b11 f
1!
#1400000
0!
#1410000
0O
1P
1J
b10011001 .
b10011001 B
b10011001 j
b10011001 n
b10000 K
1g
1,
14
1d
1b
b111 f
1!
#1420000
0!
#1430000
b110011 .
b110011 B
b110011 j
b110011 n
0,
1!
#1440000
0!
0'
0)
#1450000
0\
0d
0Z
0b
b110 ^
b110 f
1!
#1460000
0!
#1470000
b100 f
b100 ^
1!
#1480000
0!
#1490000
0_
0g
11
10
05
04
1\
1d
1[
1c
b0 ^
b0 f
1!
#1500000
0!
#1510000
01
00
1!
#1520000
0!
1)
#1530000
0d
0c
b1 f
1!
#1540000
0!
#1550000
b11 f
1!
#1560000
0!
#1570000
1Q
0P
0J
b1100110 .
b1100110 B
b1100110 j
b1100110 n
b100000 K
1g
1,
14
1d
1b
b111 f
1!
#1580000
0!
#1590000
b11001100 .
b11001100 B
b11001100 j
b11001100 n
0,
1!
#1600000
0!
1'
0)
#1610000
0\
0d
0[
0b
b1 ^
b110 f
1!
#1620000
0!
#1630000
b100 f
b11 ^
1!
#1640000
0!
#1650000
1_
0g
1-
10
15
04
1\
1d
1Z
1c
b111 ^
b0 f
1!
#1660000
0!
#1670000
0-
00
1!
#1680000
0!
1)
#1690000
0d
0c
b1 f
1!
#1700000
0!
#1710000
b11 f
1!
#1720000
0!
#1730000
0Q
1R
1J
b10011001 .
b10011001 B
b10011001 j
b10011001 n
b1000000 K
1g
1,
14
1d
1b
b111 f
1!
#1740000
0!
#1750000
b110011 .
b110011 B
b110011 j
b110011 n
0,
1!
#1760000
0!
0'
0)
#1770000
0\
0d
0Z
0b
b110 ^
b110 f
1!
#1780000
0!
#1790000
b100 f
b100 ^
1!
#1800000
0!
#1810000
0_
0g
11
10
05
04
1\
1d
1[
1c
b0 ^
b0 f
1!
#1820000
0!
#1830000
01
00
1!
#1840000
0!
1)
#1850000
0d
0c
b1 f
1!
#1860000
0!
#1870000
b11 f
1!
#1880000
0!
#1890000
17
1S
0R
0J
b1100110 .
b1100110 B
b1100110 j
b1100110 n
b10000000 K
1g
1,
14
1d
1b
b111 f
1!
#1900000
0!
#1910000
b11001100 .
b11001100 B
b11001100 j
b11001100 n
b1100110 2
b1100110 C
b1100110 k
0,
1!
#1920000
0!
1'
0)
#1930000
0\
0d
0[
0b
b1 ^
b110 f
b1001100 2
b1001100 C
b1001100 k
1!
#1940000
0!
#1950000
b101 3
b101 D
b101 l
b100 f
b11 ^
1!
#1960000
0!
#1970000
1_
0g
1-
10
15
04
1\
1d
1Z
1c
b111 ^
b0 f
1!
#1980000
0!
#1990000
0-
00
1!
#2000000
0!
1)
#2010000
0d
0c
b1 f
1!
#2020000
0!
#2030000
b11 f
1!
#2040000
0!
#2050000
07
0S
1T
1H
1J
b10011001 .
b10011001 B
b10011001 j
b10011001 n
b100000000 K
1g
1,
14
1d
1b
b111 f
1!
#2060000
0!
#2070000
b110011 .
b110011 B
b110011 j
b110011 n
0,
1!
#2080000
0!
0)
#2090000
0d
0b
b110 f
1!
#2100000
0!
#2110000
b100 f
1!
#2120000
0!
#2130000
b101 m
18
0g
10
04
1d
1c
b0 f
1!
#2140000
0!
#2150000
00
1!
#2160000
0!
1)
#2170000
0d
0c
b1 f
1!
#2180000
0!
#2190000
b11 f
1!
#2200000
0!
#2210000
1U
0T
0H
b1100111 .
b1100111 B
b1100111 j
b1100111 n
b1010 m
b1000000000 K
1g
1,
14
1d
1b
b111 f
1!
#2220000
0!
#2230000
b10100 m
b11001111 .
b11001111 B
b11001111 j
b11001111 n
0,
1!
#2240000
0!
0)
#2250000
0d
0b
b110 f
1!
#2260000
0!
#2270000
b100 f
1!
#2280000
0!
#2290000
08
0g
10
04
1d
1c
b0 f
1!
#2300000
0!
#2310000
00
1!
#2320000
0!
1)
#2330000
0d
0c
b1 f
1!
#2340000
0!
#2350000
b11 f
1!
#2360000
0!
#2370000
0U
1V
b10011111 .
b10011111 B
b10011111 j
b10011111 n
b101000 m
b10000000000 K
1g
1,
14
1d
1b
b111 f
1!
#2380000
0!
#2390000
b1010000 m
b111111 .
b111111 B
b111111 j
b111111 n
0,
1!
#2400000
0!
0'
0)
#2410000
0\
0d
0Z
0b
b110 ^
b110 f
1!
#2420000
0!
#2430000
b100 f
b100 ^
1!
#2440000
0!
#2450000
0_
0g
11
10
05
04
1\
1d
1[
1c
b0 ^
b0 f
1!
#2460000
0!
#2470000
01
00
1!
#2480000
0!
1)
#2490000
0d
0c
b1 f
1!
#2500000
0!
#2510000
b11 f
1!
#2520000
0!
#2530000
1W
0V
0J
b1111110 .
b1111110 B
b1111110 j
b1111110 n
b10100000 m
b100000000000 K
1g
1,
14
1d
1b
b111 f
1!
#2540000
0!
#2550000
b1000000 m
1*
b11111100 .
b11111100 B
b11111100 j
b11111100 n
0,
1!
#2560000
0!
1'
0)
#2570000
0\
0d
0[
0b
b1 ^
b110 f
1!
#2580000
0!
#2590000
b100 f
b11 ^
1!
#2600000
0!
#2610000
1%
1_
19
0g
1-
10
15
04
1\
1d
1Z
1c
b111 ^
b0 f
1!
#2620000
0!
#2630000
0-
00
1!
#2640000
0!
1)
#2650000
0d
0c
b1 f
1!
#2660000
0!
#2670000
b11 f
1!
#2680000
0!
#2690000
0W
1X
1J
b11111001 .
b11111001 B
b11111001 j
b11111001 n
b10000000 m
0*
b1000000000000 K
1g
1,
14
1d
1b
b111 f
1!
#2700000
0!
#2710000
b0 m
1*
b11110011 .
b11110011 B
b11110011 j
b11110011 n
0,
1!
#2720000
0!
0'
0)
#2730000
0\
0d
0Z
0b
b110 ^
b110 f
1!
#2740000
0!
#2750000
b100 f
b100 ^
1!
#2760000
0!
#2770000
0_
0g
11
10
05
04
1\
1d
1[
1c
b0 ^
b0 f
1!
#2780000
0!
#2790000
01
00
1!
#2800000
0!
1)
#2810000
0d
0c
b1 f
1!
#2820000
0!
#2830000
b11 f
1!
#2840000
0!
#2850000
1Y
0X
0J
b11100110 .
b11100110 B
b11100110 j
b11100110 n
0*
b10000000000000 K
1g
1,
14
1d
1b
b111 f
1!
#2860000
0!
#2870000
b11001100 .
b11001100 B
b11001100 j
b11001100 n
0,
1!
#2880000
0!
1'
0)
#2890000
0\
0d
0[
0b
b1 ^
b110 f
1!
#2900000
0!
