modules/enable_not.v
module enablenot(
input data_in,
input enable,
output reg out
);
always @ (enable) 
    if (enable)
        out <= ~data_in;
    else
        out <= data_in;
    
endmodule

modules/dflipflop.v
module d_flipflop(
input D,
input clk,
input enable,
output reg Q
);
    initial Q =  0;
    always @ (posedge clk) begin
        if (enable)begin
            Q <= D;
            end
         else begin
            Q <= Q;
        end
    end
endmodule

modules/addresslatch.v
module Address_Latch(
input [7:0] D,
input clk,
input enable,
output reg[6:0] Q
);
    initial Q =  0;
    always @ (posedge clk) begin
        if (enable)begin
            Q <= D[6:0];
            end
         else begin
            Q <= Q;
        end
    end
endmodule

modules/statemachine.v
//------------------------------------------------------------------------
// Finite State Machine for SPI Module
// Contributors: @aditya-sudhakar, @coreyacl, @Kristya
//------------------------------------------------------------------------

module statemachine(
    input clk,
    input cs,
    input shiftregout,
    input RW,
    output misobuff,
    output mem_we,
    output reg add_latch_we
);
parameter t_count = 15;


//SOLVE KNOWN VALUE ISSUE
reg[t_count-1:0] tim;
initial tim = 0;
wire out;
wire enable;
wire CS_N;

not notCS(CS_N,cs);


// Timer for 15
nor yep(out,tim[0],tim[1],tim[2],tim[3],tim[4],tim[5],tim[6],tim[7],tim[8],tim[9],tim[10],tim[11],tim[12],tim[13],tim[14]);
and orgate(enable,out,CS_N);

always@(posedge clk)
    tim[0] <= enable;

generate
genvar i;
for (i = 1;i<t_count ;i = i +1 ) begin
    always@(posedge clk)
        tim[i] <= tim[i-1];
end
endgenerate

// Signals the RW phase of the message
always@(tim[7]) 
    add_latch_we <= tim[7];

wire rw_enable;

// Signals end of message
and rwandgate(mem_we,RW,tim[t_count-1]);


endmodule

modules/datamemory.v
//------------------------------------------------------------------------
// Data Memory
//   Positive edge triggered
//   dataOut always has the value mem[address]
//   If writeEnable is true, writes dataIn to mem[address]
//------------------------------------------------------------------------

module datamemory
#(
    parameter addresswidth  = 7,
    parameter depth         = 2**addresswidth,
    parameter width         = 8
)
(
    input 		                clk,
    output reg [width-1:0]      dataOut,
    input [addresswidth-1:0]    address,
    input                       writeEnable,
    input [width-1:0]           dataIn,
    input                       reset
);

    reg [width-1:0] memory [depth-1:0];

    always @(posedge clk) begin
        if(writeEnable)
            memory[address] <= dataIn;
            dataOut <= memory[address];
    end


    //SO I've read that FPGAs have no known value for any registers
    //on startup so it's common practice to set a reset line to necessary
    //modules in order to set them to a known value -> Stack Overflow
    reg[31:0] k;
    always@(posedge reset)begin
      if (reset) begin
        for (k =0 ;k<3'b111 ;k = k + 1 ) begin
          memory[k] = 8'b0;
          end
          // memory[7] = 8'b101010; //points to the begening of the stack
          //                      //source -> Mars
      end
    end


endmodule

modules/shiftregmodes.v
`ifndef SHIFTREGMODES_V
`define SHIFTREGMODES_V

//List of input cases
`define HOLD      2'b00    //hold current state
`define PLOAD     2'b01    //Parallel Load: parallelIn replaces entire shift register contents
`define LSHIFT    2'b10    //Left Shift: serialIn becomes new LSB, MSB is dropped
`define RSHIFT    2'b11    //Right Shift: serialIn become the new MSB, LSB is dropped

`endif

modules/shiftregister.v
//------------------------------------------------------------------------
// Shift Register
//   Parameterized width (in bits)
//   Shift register can operate in two modes:
//      - serial in, parallel out
//      - parallel in, serial out
//------------------------------------------------------------------------

`include "shiftregmodes.v"

module shiftregister
#(parameter width = 8)
(
input               clk,                // FPGA Clock
input               peripheralClkEdge,  // Edge indicator
input               parallelLoad,       // 1 = Load shift reg with parallelDataIn
input  [width-1:0]  parallelDataIn,     // Load shift reg in parallel
input               serialDataIn,       // Load shift reg serially
output   reg [width-1:0]  parallelDataOut,    // Shift reg data contents
output              serialDataOut,      // Positive edge synchronized
output   reg        rewr                  //1 for write, 0 for read

);
    always @(parallelLoad)
        parallelDataOut <= parallelDataIn;

    always @(parallelDataIn[7])
        rewr <= parallelDataIn[7];

    always @(peripheralClkEdge) begin

        parallelDataOut <= {parallelDataOut[6:0], serialDataIn};
    end

    assign serialDataOut = parallelDataOut[width-1];

endmodule

modules/inputconditioner.v
//------------------------------------------------------------------------
// Input Conditioner
//    1) Synchronizes input to clock domain
//    2) Debounces input
//    3) Creates pulses at edge transitions
//------------------------------------------------------------------------

module inputconditioner
(
input 	    clk,            // Clock domain to synchronize input to
input	    noisysignal,    // (Potentially) noisy input signal
output reg  conditioned,    // Conditioned output signal
output reg  positiveedge,   // 1 clk pulse at rising edge of conditioned
output reg  negativeedge    // 1 clk pulse at falling edge of conditioned
);


    initial positiveedge = 0;
    initial negativeedge = 0;
    parameter counterwidth = 3; // Counter size, in bits, >= log2(waittime)
    parameter waittime = 3;     // Debounce delay, in clock cycles
    
    reg[counterwidth-1:0] counter = 0;
    reg synchronizer0 = 0;
    reg synchronizer1 = 0;
    
    reg signal;
    //Posedge for conditioned button
    always @(posedge clk) begin
        if(conditioned == synchronizer1)
            counter <= 0;

        else begin
            if( counter == waittime) begin
                counter <= 0;
                conditioned <= synchronizer1;
            end

            else 
                counter <= counter+1;
        end
        synchronizer0 <= noisysignal;
        synchronizer1 <= synchronizer0;
    end    
        //https://www.edaboard.com/showthread.php?40349-how-can-i-detect-the-positive-edge-of-a-signal-in-verilog
    always @(posedge clk or negedge conditioned)
        begin
        if (~conditioned)
            signal <= 1'b0;
        else
            signal <= 1'b1;
        assign positiveedge = conditioned & (~signal);
        assign negativeedge = ~conditioned & (signal);

        end

endmodule

modules/spimemory.v
//------------------------------------------------------------------------
// SPI Memory
//------------------------------------------------------------------------
`include "inputconditioner.v"
`include "statemachine.v"
`include "shiftregister.v"
`include "datamemory.v"
`include "addresslatch.v"
`include "dflipflop.v"
`include "enable_not.v"

module spiMemory
(
    input           clk,        // FPGA clock
    input           sclk_pin,   // SPI clock
    input           cs_pin,     // SPI chip select
    output          miso_pin,   // SPI master in slave out
    input           mosi_pin,   // SPI master out slave in
    output [3:0]    leds        // LEDs for debugging
);
    wire[7:0] dataMemOut;
    wire Q_S_out;
    wire cond_cs;
    wire cond_sclk;
    wire cond_mosi;
    wire posedge0;
    wire posedge1; 
    wire posedge2;
    wire negedge0;
    wire negedge1;
    wire negedge2;
    wire[6:0] data_address;
    wire[7:0] parallelDataOut;
    wire serialDataOut;

    wire RW;
    wire misobuff;
    wire mem_we;
    wire add_latch_we;

    inputconditioner MOSI_cond(.conditioned(cond_mosi), .positiveedge(posedge0), .negativeedge(negedge0), .noisysignal(mosi_pin), .clk(clk));
    inputconditioner SCLK_cond(.conditioned(cond_sclk), .positiveedge(posedge1), .negativeedge(negedge1), .noisysignal(sclk_pin), .clk(clk));
    inputconditioner CS_cond(.conditioned(cond_cs), .positiveedge(posedge2), .negativeedge(negedge2), .noisysignal(cs_pin), .clk(clk));

    shiftregister shift_register(.peripheralClkEdge(posedge1), .parallelLoad(RW), .parallelDataIn(dataMemOut), .serialDataIn(cond_mosi), .parallelDataOut(parallelDataOut), .serialDataOut(serialDataOut), .rewr(RW), .clk(clk));

 
    datamemory Data_Memory(.dataOut(dataMemOut), .address(data_address), .writeEnable(mem_we), .dataIn(parallelDataOut), .clk(clk));
  


    statemachine FSM(.misobuff(misobuff), .mem_we(mem_we), .add_latch_we(add_latch_we), .RW(RW), .shiftregout(parallelDataOut[0]), .cs(cond_cs), .clk(clk));



    Address_Latch addr_latch(.Q(data_address), .D(parallelDataOut), .enable(add_latch_we), .clk(clk));


    d_flipflop DFF(.Q(Q_S_out), .D(serialDataOut), .enable(negedge1), .clk(clk));

    enablenot e_not(.out(miso_pin), .enable(misobuff), .data_in(Q_S_out));

endmodule

modules/spimemory.t.v
`include "spimemory.v"

module SPI_Test();    
    reg           clk;       // FPGA clock
    reg           sclk_pin;   // SPI clock
    reg           cs_pin;     // SPI chip select
    wire          miso_pin;   // SPI master in slave out
    reg           mosi_pin;   // SPI master out slave in

    spiMemory dut(.miso_pin(miso_pin), 
                  .mosi_pin(mosi_pin),
                  .cs_pin(cs_pin),
                  .sclk_pin(sclk_pin),
                  .clk(clk));

    // Generate clock (50MHz)
    initial clk = 0;
    always #10 clk=!clk;    // 50MHz Clock
    
        initial begin
        $dumpfile("spimemory.vcd");
        $dumpvars(0, dut);
        $display("testing");
		$monitor("| %b | %b | %b | %b | %b |", clk, sclk_pin, mosi_pin, cs_pin, miso_pin);
		mosi_pin=1'b0; sclk_pin = 1'b0; cs_pin = 8'b0; #100

		mosi_pin=1'b1; sclk_pin = 1'b0; cs_pin = 8'b0; #100

		mosi_pin=1'b1; sclk_pin = 1'b1; cs_pin = 8'b0; #100

	    mosi_pin=1'b0; sclk_pin = 1'b1; cs_pin = 8'b0; #100

		mosi_pin=1'b0; sclk_pin = 1'b0; cs_pin = 8'b0; #100

		mosi_pin=1'b0; sclk_pin = 1'b0; cs_pin = 8'b0; #100

		mosi_pin=1'b0; sclk_pin = 1'b1; cs_pin = 8'b0; #100

	    mosi_pin=1'b0; sclk_pin = 1'b1; cs_pin = 8'b0; #100

		$display("END");
        $finish();
	end
endmodule

modules/spimemory.vcd
$date
	Tue Nov 19 16:18:52 2019
$end
$version
	Icarus Verilog
$end
$timescale
	1s
$end
$scope module SPI_Test $end
$scope module dut $end
$var wire 1 ! clk $end
$var wire 1 " cs_pin $end
$var wire 4 # leds [3:0] $end
$var wire 1 $ misobuff $end
$var wire 1 % mosi_pin $end
$var wire 1 & sclk_pin $end
$var wire 1 ' serialDataOut $end
$var wire 1 ( posedge2 $end
$var wire 1 ) posedge1 $end
$var wire 1 * posedge0 $end
$var wire 8 + parallelDataOut [7:0] $end
$var wire 1 , negedge2 $end
$var wire 1 - negedge1 $end
$var wire 1 . negedge0 $end
$var wire 1 / miso_pin $end
$var wire 1 0 mem_we $end
$var wire 7 1 data_address [6:0] $end
$var wire 8 2 dataMemOut [7:0] $end
$var wire 1 3 cond_sclk $end
$var wire 1 4 cond_mosi $end
$var wire 1 5 cond_cs $end
$var wire 1 6 add_latch_we $end
$var wire 1 7 RW $end
$var wire 1 8 Q_S_out $end
$scope module CS_cond $end
$var wire 1 ! clk $end
$var wire 1 " noisysignal $end
$var reg 1 5 conditioned $end
$var reg 3 9 counter [2:0] $end
$var reg 1 , negativeedge $end
$var reg 1 ( positiveedge $end
$var reg 1 : signal $end
$var reg 1 ; synchronizer0 $end
$var reg 1 < synchronizer1 $end
$upscope $end
$scope module DFF $end
$var wire 1 ! clk $end
$var wire 1 - enable $end
$var wire 1 ' D $end
$var reg 1 8 Q $end
$upscope $end
$scope module Data_Memory $end
$var wire 1 ! clk $end
$var wire 1 = reset $end
$var wire 1 0 writeEnable $end
$var wire 8 > dataIn [7:0] $end
$var wire 7 ? address [6:0] $end
$var reg 8 @ dataOut [7:0] $end
$var reg 32 A k [31:0] $end
$upscope $end
$scope module FSM $end
$var wire 1 B CS_N $end
$var wire 1 ! clk $end
$var wire 1 5 cs $end
$var wire 1 C enable $end
$var wire 1 0 mem_we $end
$var wire 1 $ misobuff $end
$var wire 1 D out $end
$var wire 1 E shiftregout $end
$var wire 1 7 RW $end
$var reg 1 6 add_latch_we $end
$var reg 15 F tim [14:0] $end
$scope begin genblk1[1] $end
$upscope $end
$scope begin genblk1[2] $end
$upscope $end
$scope begin genblk1[3] $end
$upscope $end
$scope begin genblk1[4] $end
$upscope $end
$scope begin genblk1[5] $end
$upscope $end
$scope begin genblk1[6] $end
$upscope $end
$scope begin genblk1[7] $end
$upscope $end
$scope begin genblk1[8] $end
$upscope $end
$scope begin genblk1[9] $end
$upscope $end
$scope begin genblk1[10] $end
$upscope $end
$scope begin genblk1[11] $end
$upscope $end
$scope begin genblk1[12] $end
$upscope $end
$scope begin genblk1[13] $end
$upscope $end
$scope begin genblk1[14] $end
$upscope $end
$upscope $end
$scope module MOSI_cond $end
$var wire 1 ! clk $end
$var wire 1 % noisysignal $end
$var reg 1 4 conditioned $end
$var reg 3 G counter [2:0] $end
$var reg 1 . negativeedge $end
$var reg 1 * positiveedge $end
$var reg 1 H signal $end
$var reg 1 I synchronizer0 $end
$var reg 1 J synchronizer1 $end
$upscope $end
$scope module SCLK_cond $end
$var wire 1 ! clk $end
$var wire 1 & noisysignal $end
$var reg 1 3 conditioned $end
$var reg 3 K counter [2:0] $end
$var reg 1 - negativeedge $end
$var reg 1 ) positiveedge $end
$var reg 1 L signal $end
$var reg 1 M synchronizer0 $end
$var reg 1 N synchronizer1 $end
$upscope $end
$scope module addr_latch $end
$var wire 1 ! clk $end
$var wire 1 6 enable $end
$var wire 8 O D [7:0] $end
$var reg 7 P Q [6:0] $end
$upscope $end
$scope module e_not $end
$var wire 1 8 data_in $end
$var wire 1 $ enable $end
$var reg 1 / out $end
$upscope $end
$scope module shift_register $end
$var wire 1 ! clk $end
$var wire 8 Q parallelDataIn [7:0] $end
$var wire 1 ) peripheralClkEdge $end
$var wire 1 4 serialDataIn $end
$var wire 1 ' serialDataOut $end
$var wire 1 7 parallelLoad $end
$var reg 8 R parallelDataOut [7:0] $end
$var reg 1 7 rewr $end
$upscope $end
$upscope $end
$upscope $end
$enddefinitions $end
#0
$dumpvars
bx0 R
bx Q
b0 P
bx0 O
0N
0M
xL
b0 K
0J
0I
xH
b0 G
b0 F
0E
1D
1C
1B
bx A
bx @
b0 ?
bx0 >
z=
0<
0;
x:
b0 9
08
x7
06
05
04
03
bx 2
b0 1
00
0/
0.
0-
0,
bx0 +
0*
0)
0(
x'
0&
0%
z$
bz #
1"
0!
$end
#10
0C
0D
0:
1;
b1 F
0H
0L
x,
x.
x-
1!
#20
0!
#30
b10 F
1<
0,
0.
0-
1!
#40
0!
#50
b1 9
b100 F
1!
#60
0!
#70
b1000 F
b10 9
1!
#80
0!
1&
#90
1M
b11 9
b10000 F
1!
#100
0!
#110
1:
1(
0B
b100000 F
15
b0 9
1N
1!
#120
0!
#130
b1 K
b1000000 F
0(
1!
#140
0!
#150
16
b10000000 F
b10 K
1!
#160
0!
0&
#170
06
0M
b11 K
b100000000 F
bx0 1
bx0 ?
bx0 P
1!
#180
0!
#190
bx00 +
bx00 >
bx00 O
bx00 R
1L
1)
b1000000000 F
0N
13
b0 K
1!
#200
0!
#210
bx000 +
bx000 >
bx000 O
bx000 R
b1 K
b10000000000 F
0)
1!
#220
0!
#230
b100000000000 F
b10 K
1!
#240
0!
1&
#250
1M
b11 K
b1000000000000 F
1!
#260
0!
#270
0L
1-
b10000000000000 F
1N
03
b0 K
1!
#280
0!
#290
x0
b1 K
b100000000000000 F
0-
1!
#300
0!
#310
1D
00
b0 F
b10 K
1!
#320
0!
0&
#330
0M
b11 K
1!
#340
0!
#350
bx0000 +
bx0000 >
bx0000 O
bx0000 R
1L
1)
0N
13
b0 K
1!
#360
0!
#370
bx00000 +
bx00000 >
bx00000 O
bx00000 R
b1 K
0)
1!
#380
0!
#390
b10 K
1!
#400
0!
1&
#410
1M
b11 K
1!
#420
0!
#430
0L
1-
1N
03
b0 K
1!
#440
0!
#450
b1 K
0-
1!
#460
0!
#470
b10 K
1!
#480
0!
0&
#490
0M
b11 K
1!
#500
0!
#510
bx000000 +
bx000000 >
bx000000 O
bx000000 R
1L
1)
0N
13
b0 K
1!
#520
0!
#530
bx0000000 +
bx0000000 >
bx0000000 O
bx0000000 R
b1 K
0)
1!
#540
0!
#550
b10 K
1!
#560
0!
1&
#570
1M
b11 K
1!
#580
0!
#590
0L
1-
1N
03
b0 K
1!
#600
0!
#610
b1 K
0-
1!
#620
0!
#630
b10 K
1!
#640
0!
0"
1%
0&
#650
1I
0M
b11 K
0;
1!
#660
0!
#670
0'
b0 +
b0 >
b0 O
b0 R
1L
1)
0<
0N
13
b0 K
1J
1!
#680
0!
#690
b1 G
b1 K
b1 9
0)
1!
#700
0!
#710
b10 9
b10 K
b10 G
1!
#720
0!
1&
#730
b11 G
1M
b11 K
b11 9
1!
#740
0!
#750
0:
0L
1H
1C
1,
1B
1-
1*
05
b0 9
1N
03
b0 K
14
b0 G
1!
#760
0!
#770
0C
0D
b1 K
b1 F
0,
0*
0-
1!
#780
0!
#790
b10 F
b10 K
1!
#800
0!
0%
0&
#810
0I
0M
b11 K
b100 F
1!
#820
0!
#830
1E
b1 +
b1 >
b1 O
b1 R
1L
1)
b1000 F
0N
13
b0 K
0J
1!
#840
0!
#850
b11 +
b11 >
b11 O
b11 R
b1 G
b1 K
b10000 F
0)
1!
#860
0!
#870
b100000 F
b10 K
b10 G
1!
#880
0!
1&
#890
b11 G
1M
b11 K
b1000000 F
1!
#900
0!
#910
16
0L
0H
1-
1.
b10000000 F
1N
03
b0 K
04
b0 G
1!
#920
0!
#930
06
b1 K
b100000000 F
b11 1
b11 ?
b11 P
0.
0-
1!
#940
0!
#950
b1000000000 F
b10 K
1!
#960
0!
1%
0&
#970
1I
0M
b11 K
b10000000000 F
1!
#980
0!
#990
0E
b110 +
b110 >
b110 O
b110 R
1L
1)
b100000000000 F
0N
13
b0 K
1J
1!
#1000
0!
#1010
b1100 +
b1100 >
b1100 O
b1100 R
b1 G
b1 K
b1000000000000 F
0)
1!
#1020
0!
#1030
b10000000000000 F
b10 K
b10 G
1!
#1040
0!
1&
#1050
x0
b11 G
1M
b11 K
b100000000000000 F
1!
#1060
0!
#1070
0L
1H
1C
1D
00
1-
1*
b0 F
1N
03
b0 K
14
b0 G
1!
#1080
0!
#1090
0C
0D
b1 K
b1 F
0*
0-
1!
#1100
0!
#1110
b10 F
b10 K
1!
#1120
0!
0%
0&
#1130
0I
0M
b11 K
b100 F
1!
#1140
0!
#1150
1E
b11001 +
b11001 >
b11001 O
b11001 R
1L
1)
b1000 F
0N
13
b0 K
0J
1!
#1160
0!
#1170
b110011 +
b110011 >
b110011 O
b110011 R
b1 G
b1 K
b10000 F
0)
1!
#1180
0!
#1190
b100000 F
b10 K
b10 G
1!
#1200
0!
1&
#1210
b11 G
1M
b11 K
b1000000 F
1!
#1220
0!
#1230
16
0L
0H
1-
1.
b10000000 F
1N
03
b0 K
04
b0 G
1!
#1240
0!
#1250
06
b1 K
b100000000 F
b110011 1
b110011 ?
b110011 P
0.
0-
1!
#1260
0!
#1270
b1000000000 F
b10 K
1!
#1280
0!
1%
0&
#1290
1I
0M
b11 K
b10000000000 F
1!
#1300
0!
#1310
0E
b1100110 +
b1100110 >
b1100110 O
b1100110 R
1L
1)
b100000000000 F
0N
13
b0 K
1J
1!
#1320
0!
#1330
1'
b11001100 +
b11001100 >
b11001100 O
b11001100 R
b1 G
b1 K
b1000000000000 F
0)
1!
#1340
0!
#1350
b10000000000000 F
b10 K
b10 G
1!
#1360
0!
1&
#1370
x0
b11 G
1M
b11 K
b100000000000000 F
1!
#1380
0!
#1390
0L
1H
1C
1D
00
1-
1*
b0 F
1N
03
b0 K
14
b0 G
1!
#1400
0!
#1410
0C
0D
b1 K
b1 F
0*
0-
1!
#1420
0!
#1430
b10 F
b10 K
1!
#1440
0!
0%
0&
#1450
0I
0M
b11 K
b100 F
1!
#1460
0!
#1470
1E
b10011001 +
b10011001 >
b10011001 O
b10011001 R
1L
1)
b1000 F
0N
13
b0 K
0J
1!
#1480
0!
#1490
0'
b110011 +
b110011 >
b110011 O
b110011 R
b1 G
b1 K
b10000 F
0)
1!
#1500
0!
#1510
b100000 F
b10 K
b10 G
1!
#1520
0!
1&
#1530
b11 G
1M
b11 K
b1000000 F
1!
#1540
0!
#1550
16
0L
0H
1-
1.
b10000000 F
1N
03
b0 K
04
b0 G
1!
#1560
0!
#1570
06
b1 K
b100000000 F
0.
0-
1!
#1580
0!
#1590
b1000000000 F
b10 K
1!
#1600
0!
1%
0&
#1610
1I
0M
b11 K
b10000000000 F
1!
#1620
0!
#1630
0E
b1100110 +
b1100110 >
b1100110 O
b1100110 R
1L
1)
b100000000000 F
0N
13
b0 K
1J
1!
#1640
0!
#1650
1'
b11001100 +
b11001100 >
b11001100 O
b11001100 R
b1 G
b1 K
b1000000000000 F
0)
1!
#1660
0!
#1670
b10000000000000 F
b10 K
b10 G
1!
#1680
0!
1&
#1690
x0
b11 G
1M
b11 K
b100000000000000 F
1!
#1700
0!
#1710
0L
1H
1C
1D
00
1-
1*
b0 F
1N
03
b0 K
14
b0 G
1!
#1720
0!
#1730
0C
0D
b1 K
b1 F
0*
0-
1!
#1740
0!
#1750
b10 F
b10 K
1!
#1760
0!
0%
0&
#1770
0I
0M
b11 K
b100 F
1!
#1780
0!
#1790
1E
b10011001 +
b10011001 >
b10011001 O
b10011001 R
1L
1)
b1000 F
0N
13
b0 K
0J
1!
#1800
0!
#1810
0'
b110011 +
b110011 >
b110011 O
b110011 R
b1 G
b1 K
b10000 F
0)
1!
#1820
0!
#1830
b100000 F
b10 K
b10 G
1!
#1840
0!
1&
#1850
b11 G
1M
b11 K
b1000000 F
1!
#1860
0!
#1870
16
0L
0H
1-
1.
b10000000 F
1N
03
b0 K
04
b0 G
1!
#1880
0!
#1890
06
b1 K
b100000000 F
0.
0-
1!
#1900
0!
#1910
b1000000000 F
b10 K
1!
#1920
0!
1"
0&
#1930
0M
b11 K
1;
b10000000000 F
1!
#1940
0!
#1950
0E
b1100110 +
b1100110 >
b1100110 O
b1100110 R
1L
1)
b100000000000 F
1<
0N
13
b0 K
1!
#1960
0!
#1970
1'
b11001100 +
b11001100 >
b11001100 O
b11001100 R
b1 K
b1 9
b1000000000000 F
0)
1!
#1980
0!
#1990
b10000000000000 F
b10 9
b10 K
1!
#2000
0!
1&
#2010
x0
1M
b11 K
b11 9
b100000000000000 F
1!
#2020
0!
#2030
1:
0L
1D
00
1(
0B
1-
b0 F
15
b0 9
1N
03
b0 K
1!
#2040
0!
#2050
b1 K
0(
0-
1!
#2060
0!
#2070
b10 K
1!
#2080
0!
0&
#2090
0M
b11 K
1!
#2100
0!
#2110
b10011000 +
b10011000 >
b10011000 O
b10011000 R
1L
1)
0N
13
b0 K
1!
#2120
0!
#2130
0'
b110000 +
b110000 >
b110000 O
b110000 R
b1 K
0)
1!
#2140
0!
#2150
b10 K
1!
#2160
0!
1&
#2170
1M
b11 K
1!
#2180
0!
#2190
0L
1-
1N
03
b0 K
1!
#2200
0!
#2210
b1 K
0-
1!
#2220
0!
#2230
b10 K
1!
#2240
0!
0&
#2250
0M
b11 K
1!
#2260
0!
#2270
b1100000 +
b1100000 >
b1100000 O
b1100000 R
1L
1)
0N
13
b0 K
1!
#2280
0!
#2290
1'
b11000000 +
b11000000 >
b11000000 O
b11000000 R
b1 K
0)
1!
#2300
0!
#2310
b10 K
1!
#2320
0!
1&
#2330
1M
b11 K
1!
#2340
0!
#2350
0L
1-
1N
03
b0 K
1!
#2360
0!
#2370
b1 K
0-
1!
#2380
0!
#2390
b10 K
1!
#2400
0!
0&
#2410
0M
b11 K
1!
#2420
0!
#2430
b10000000 +
b10000000 >
b10000000 O
b10000000 R
1L
1)
0N
13
b0 K
1!
#2440
0!
#2450
0'
b0 +
b0 >
b0 O
b0 R
b1 K
0)
1!
#2460
0!
#2470
b10 K
1!
#2480
0!
1&
#2490
1M
b11 K
1!
#2500
0!
#2510
0L
1-
1N
03
b0 K
1!
#2520
0!
#2530
b1 K
0-
1!
#2540
0!
#2550
b10 K
1!
#2560
0!
0&
#2570
0M
b11 K
1!
#2580
0!
#2590
1L
1)
0N
13
b0 K
1!
#2600
0!
#2610
b1 K
0)
1!
#2620
0!
#2630
b10 K
1!
#2640
0!
1&
#2650
1M
b11 K
1!
#2660
0!
#2670
0L
1-
1N
03
b0 K
1!
#2680
0!
#2690
b1 K
0-
1!
#2700
0!
#2710
b10 K
1!
#2720
0!
0&
#2730
0M
b11 K
1!
#2740
0!
#2750
1L
1)
0N
13
b0 K
1!
#2760
0!
#2770
b1 K
0)
1!
#2780
0!
#2790
b10 K
1!
#2800
0!
1&
#2810
1M
b11 K
1!
#2820
0!
#2830
0L
1-
1N
03
b0 K
1!
#2840
0!
#2850
b1 K
0-
1!
#2860
0!
#2870
b10 K
1!
#2880
0!
0&
#2890
0M
b11 K
1!
#2900
0!
#2910
1L
1)
0N
13
b0 K
1!
#2920
0!
#2930
b1 K
0)
1!
#2940
0!
#2950
b10 K
1!
#2960
0!
1&
#2970
1M
b11 K
1!
#2980
0!
#2990
0L
1-
1N
03
b0 K
1!
#3000
0!
#3010
b1 K
0-
1!
#3020
0!
#3030
b10 K
1!
#3040
0!
0&
#3050
0M
b11 K
1!
#3060
0!
#3070
1L
1)
0N
13
b0 K
1!
#3080
0!
#3090
b1 K
0)
1!
#3100
0!
#3110
b10 K
1!
#3120
0!
1&
#3130
1M
b11 K
1!
#3140
0!
#3150
0L
1-
1N
03
b0 K
1!
#3160
0!
#3170
b1 K
0-
1!
#3180
0!
#3190
b10 K
1!
#3200
0!
0&
#3210
0M
b11 K
1!
#3220
0!
#3230
1L
1)
0N
13
b0 K
1!
#3240
0!
#3250
b1 K
0)
1!
#3260
0!
#3270
b10 K
1!
#3280
0!
1&
#3290
1M
b11 K
1!
#3300
0!
#3310
0L
1-
1N
03
b0 K
1!
#3320
0!
#3330
b1 K
0-
1!
#3340
0!
#3350
b10 K
1!
#3360
0!
0&
#3370
0M
b11 K
1!
#3380
0!
#3390
1L
1)
0N
13
b0 K
1!
#3400
0!
#3410
b1 K
0)
1!
#3420
0!
#3430
b10 K
1!
#3440
0!
1&
#3450
1M
b11 K
1!
#3460
0!
#3470
0L
1-
1N
03
b0 K
1!
#3480
0!
#3490
b1 K
0-
1!
#3500
0!
#3510
b10 K
1!
#3520
0!
0&
#3530
0M
b11 K
1!
#3540
0!
#3550
1L
1)
0N
13
b0 K
1!
#3560
0!
#3570
b1 K
0)
1!
#3580
0!
#3590
b10 K
1!
#3600
0!
1&
#3610
1M
b11 K
1!
#3620
0!
#3630
0L
1-
1N
03
b0 K
1!
#3640
0!
#3650
b1 K
0-
1!
#3660
0!
#3670
b10 K
1!
#3680
0!
0&
#3690
0M
b11 K
1!
#3700
0!
#3710
1L
1)
0N
13
b0 K
1!
#3720
0!
#3730
b1 K
0)
1!
#3740
0!
#3750
b10 K
1!
#3760
0!
1&
#3770
1M
b11 K
1!
#3780
0!
#3790
0L
1-
1N
03
b0 K
1!
#3800
0!
#3810
b1 K
0-
1!
#3820
0!
#3830
b10 K
1!
#3840
0!
0&
#3850
0M
b11 K
1!
#3860
0!
#3870
1L
1)
0N
13
b0 K
1!
#3880
0!
#3890
b1 K
0)
1!
#3900
0!
#3910
b10 K
1!
#3920
0!
1&
#3930
1M
b11 K
1!
#3940
0!
#3950
0L
1-
1N
03
b0 K
1!
#3960
0!
#3970
b1 K
0-
1!
#3980
0!
#3990
b10 K
1!
#4000
0!
0&
#4010
0M
b11 K
1!
#4020
0!
#4030
1L
1)
0N
13
b0 K
1!
#4040
0!
#4050
b1 K
0)
1!
#4060
0!
#4070
b10 K
1!
#4080
0!
1&
#4090
1M
b11 K
1!
#4100
0!
#4110
0L
1-
1N
03
b0 K
1!
#4120
0!
#4130
b1 K
0-
1!
#4140
0!
#4150
b10 K
1!
#4160
0!
0&
#4170
0M
b11 K
1!
#4180
0!
#4190
1L
1)
0N
13
b0 K
1!
#4200
0!
#4210
b1 K
0)
1!
#4220
0!
#4230
b10 K
1!
#4240
0!
1&
#4250
1M
b11 K
1!
#4260
0!
#4270
0L
1-
1N
03
b0 K
1!
#4280
0!
#4290
b1 K
0-
1!
#4300
0!
#4310
b10 K
1!
#4320
0!
0&
#4330
0M
b11 K
1!
#4340
0!
#4350
1L
1)
0N
13
b0 K
1!
#4360
0!
#4370
b1 K
0)
1!
#4380
0!
#4390
b10 K
1!
#4400
0!
1&
#4410
1M
b11 K
1!
#4420
0!
#4430
0L
1-
1N
03
b0 K
1!
#4440
0!
#4450
b1 K
0-
1!
#4460
0!
#4470
b10 K
1!
#4480
0!
0&
#4490
0M
b11 K
1!
#4500
0!
#4510
1L
1)
0N
13
b0 K
1!
#4520
0!
#4530
b1 K
0)
1!
#4540
0!
#4550
b10 K
1!
#4560
0!
1&
#4570
1M
b11 K
1!
#4580
0!
#4590
0L
1-
1N
03
b0 K
1!
#4600
0!
#4610
b1 K
0-
1!
#4620
0!
#4630
b10 K
1!
#4640
0!
0&
#4650
0M
b11 K
1!
#4660
0!
#4670
1L
1)
0N
13
b0 K
1!
#4680
0!
#4690
b1 K
0)
1!
#4700
0!
#4710
b10 K
1!
#4720
0!
1&
#4730
1M
b11 K
1!
#4740
0!
#4750
0L
1-
1N
03
b0 K
1!
#4760
0!
#4770
b1 K
0-
1!
#4780
0!
#4790
b10 K
1!
#4800
0!
0&
#4810
0M
b11 K
1!
#4820
0!
#4830
1L
1)
0N
13
b0 K
1!
#4840
0!
#4850
b1 K
0)
1!
#4860
0!
#4870
b10 K
1!
#4880
0!
1&
#4890
1M
b11 K
1!
#4900
0!
#4910
0L
1-
1N
03
b0 K
1!
#4920
0!
#4930
b1 K
0-
1!
#4940
0!
#4950
b10 K
1!
#4960
0!
0&
#4970
0M
b11 K
1!
#4980
0!
#4990
1L
1)
0N
13
b0 K
1!
#5000
0!
#5010
b1 K
0)
1!
#5020
0!
#5030
b10 K
1!
#5040
0!
1&
#5050
1M
b11 K
1!
#5060
0!
#5070
0L
1-
1N
03
b0 K
1!
#5080
0!
#5090
b1 K
0-
1!
#5100
0!
#5110
b10 K
1!
#5120
0!
0&
#5130
0M
b11 K
1!
#5140
0!
#5150
1L
1)
0N
13
b0 K
1!
#5160
0!
#5170
b1 K
0)
1!
#5180
0!
#5190
b10 K
1!
#5200
0!
1&
#5210
1M
b11 K
1!
#5220
0!
#5230
0L
1-
1N
03
b0 K
1!
#5240
0!
#5250
b1 K
0-
1!
#5260
0!
#5270
b10 K
1!
#5280
0!
0&
#5290
0M
b11 K
1!
#5300
0!
#5310
1L
1)
0N
13
b0 K
1!
#5320
0!
#5330
b1 K
0)
1!
#5340
0!
#5350
b10 K
1!
#5360
0!
1&
#5370
1M
b11 K
1!
#5380
0!
