modules/statemachine.v
//------------------------------------------------------------------------
// Finite State Machine for SPI Module
// Contributors: @aditya-sudhakar, @coreyacl, @Kristya
//------------------------------------------------------------------------

module statemachine(
    input clk,
    input cs,
    input shiftregout,
    output reg RW,
    output misobuff,
    output mem_we,
    output reg add_latch_we,
    input serialDataIn
);
parameter t_count = 15;


//SOLVE KNOWN VALUE ISSUE
reg[t_count-1:0] tim;
initial tim = 0;
wire out;
wire enable;
wire CS_N;

not notCS(CS_N,cs);


// Timer for 15
nor yep(out,tim[0],tim[1],tim[2],tim[3],tim[4],tim[5],tim[6],tim[7],tim[8],tim[9],tim[10],tim[11],tim[12],tim[13],tim[14]);
and orgate(enable,out,CS_N);

always@(posedge clk)
    tim[0] <= enable;

generate
genvar i;
for (i = 1;i<t_count ;i = i +1 ) begin
wire res;
and andgateTimer(res,CS_N,tim[i-1]);
    always@(posedge clk)
        tim[i] <= res;
end
endgenerate

// Signals the RW phase of the message
always@(tim[7])
    add_latch_we <= tim[7];

wire rw_enable;

wire ifRead;

and andgate1(ifRead,tim[8],serialDataIn);

// Load parallel data in
always@(negedge clk)
    RW <= ifRead;

// Signals end of message
// and rwandgate(mem_we,RW,tim[t_count-1]);


endmodule

modules/statemachine.t.v
`timescale 1 ns  / 1 ns

`include "statemachine.v"


module TAKS();

    reg clk;
    reg cs;

    initial clk = 0;
    always #5 clk= !clk;

    statemachine fsm(
        .clk(clk),
        .cs(cs),
        .shiftregout(),
        .misobuff(),
        .mem_we(),
        .add_latch_we(),
        .RW(rw)
    );

    initial begin
        $dumpfile("statemachine.vcd");
        $dumpvars();
        $display("Testing Begin...");
        cs = 1;
        #105
        cs = 0;
        #150
        cs = 1;
        #100
        $display("View GTKwave for information");

        $finish();
    end
endmodule

modules/statemachine.vcd
$date
	Tue Nov 19 17:35:48 2019
$end
$version
	Icarus Verilog
$end
$timescale
	1ns
$end
$scope module TAKS $end
$var wire 1 ! rw $end
$var reg 1 " clk $end
$var reg 1 # cs $end
$scope module fsm $end
$var wire 1 $ CS_N $end
$var wire 1 " clk $end
$var wire 1 # cs $end
$var wire 1 % enable $end
$var wire 1 & ifRead $end
$var wire 1 ' mem_we $end
$var wire 1 ( misobuff $end
$var wire 1 ) out $end
$var wire 1 * serialDataIn $end
$var wire 1 + shiftregout $end
$var reg 1 ! RW $end
$var reg 1 , add_latch_we $end
$var reg 15 - tim [14:0] $end
$scope begin genblk1[1] $end
$var wire 1 . res $end
$upscope $end
$scope begin genblk1[2] $end
$var wire 1 / res $end
$upscope $end
$scope begin genblk1[3] $end
$var wire 1 0 res $end
$upscope $end
$scope begin genblk1[4] $end
$var wire 1 1 res $end
$upscope $end
$scope begin genblk1[5] $end
$var wire 1 2 res $end
$upscope $end
$scope begin genblk1[6] $end
$var wire 1 3 res $end
$upscope $end
$scope begin genblk1[7] $end
$var wire 1 4 res $end
$upscope $end
$scope begin genblk1[8] $end
$var wire 1 5 res $end
$upscope $end
$scope begin genblk1[9] $end
$var wire 1 6 res $end
$upscope $end
$scope begin genblk1[10] $end
$var wire 1 7 res $end
$upscope $end
$scope begin genblk1[11] $end
$var wire 1 8 res $end
$upscope $end
$scope begin genblk1[12] $end
$var wire 1 9 res $end
$upscope $end
$scope begin genblk1[13] $end
$var wire 1 : res $end
$upscope $end
$scope begin genblk1[14] $end
$var wire 1 ; res $end
$upscope $end
$upscope $end
$upscope $end
$enddefinitions $end
#0
$dumpvars
0;
0:
09
08
07
06
05
04
03
02
01
00
0/
0.
b0 -
0,
z+
z*
1)
z(
z'
0&
0%
0$
1#
0"
x!
$end
#5
1"
#10
0!
0"
#15
1"
#20
0"
#25
1"
#30
0"
#35
1"
#40
0"
#45
1"
#50
0"
#55
1"
#60
0"
#65
1"
#70
0"
#75
1"
#80
0"
#85
1"
#90
0"
#95
1"
#100
0"
#105
1%
1$
1"
0#
#110
0"
#115
0%
0)
1.
b1 -
1"
#120
0"
#125
1/
0.
b10 -
1"
#130
0"
#135
10
0/
b100 -
1"
#140
0"
#145
00
11
b1000 -
1"
#150
0"
#155
12
01
b10000 -
1"
#160
0"
#165
02
13
b100000 -
1"
#170
0"
#175
14
03
b1000000 -
1"
#180
0"
#185
1,
04
15
x&
b10000000 -
1"
#190
x!
0"
#195
0,
16
05
0&
b100000000 -
1"
#200
0!
0"
#205
06
17
b1000000000 -
1"
#210
0"
#215
18
07
b10000000000 -
1"
#220
0"
#225
08
19
b100000000000 -
1"
#230
0"
#235
1:
09
b1000000000000 -
1"
#240
0"
#245
0:
1;
b10000000000000 -
1"
#250
0"
#255
b100000000000000 -
0;
0$
1"
1#
#260
0"
#265
1)
b0 -
1"
